package com.alibaba.mtl.log.e;

public final class e
{
  static
  {
    System.setProperty("http.keepAlive", "true");
  }
  
  /* Error */
  public static a a(int paramInt, String paramString, java.util.Map<String, Object> paramMap, boolean paramBoolean)
  {
    // Byte code:
    //   0: new 6	com/alibaba/mtl/log/e/e$a
    //   3: dup
    //   4: invokespecial 32	com/alibaba/mtl/log/e/e$a:<init>	()V
    //   7: astore 6
    //   9: aload_1
    //   10: invokestatic 38	android/text/TextUtils:isEmpty	(Ljava/lang/CharSequence;)Z
    //   13: ifeq +6 -> 19
    //   16: aload 6
    //   18: areturn
    //   19: new 40	java/net/URL
    //   22: dup
    //   23: aload_1
    //   24: invokespecial 43	java/net/URL:<init>	(Ljava/lang/String;)V
    //   27: invokevirtual 47	java/net/URL:openConnection	()Ljava/net/URLConnection;
    //   30: checkcast 49	java/net/HttpURLConnection
    //   33: astore 7
    //   35: aload 7
    //   37: ifnull +835 -> 872
    //   40: iload_0
    //   41: iconst_2
    //   42: if_icmpeq +8 -> 50
    //   45: iload_0
    //   46: iconst_3
    //   47: if_icmpne +9 -> 56
    //   50: aload 7
    //   52: iconst_1
    //   53: invokevirtual 53	java/net/HttpURLConnection:setDoOutput	(Z)V
    //   56: aload 7
    //   58: iconst_1
    //   59: invokevirtual 56	java/net/HttpURLConnection:setDoInput	(Z)V
    //   62: iload_0
    //   63: iconst_2
    //   64: if_icmpeq +8 -> 72
    //   67: iload_0
    //   68: iconst_3
    //   69: if_icmpne +262 -> 331
    //   72: aload 7
    //   74: ldc 58
    //   76: invokevirtual 61	java/net/HttpURLConnection:setRequestMethod	(Ljava/lang/String;)V
    //   79: aload 7
    //   81: iconst_0
    //   82: invokevirtual 64	java/net/HttpURLConnection:setUseCaches	(Z)V
    //   85: aload 7
    //   87: sipush 10000
    //   90: invokevirtual 68	java/net/HttpURLConnection:setConnectTimeout	(I)V
    //   93: aload 7
    //   95: ldc 69
    //   97: invokevirtual 72	java/net/HttpURLConnection:setReadTimeout	(I)V
    //   100: aload 7
    //   102: ldc 74
    //   104: ldc 76
    //   106: invokevirtual 80	java/net/HttpURLConnection:setRequestProperty	(Ljava/lang/String;Ljava/lang/String;)V
    //   109: iload_3
    //   110: ifeq +12 -> 122
    //   113: aload 7
    //   115: ldc 82
    //   117: ldc 84
    //   119: invokevirtual 80	java/net/HttpURLConnection:setRequestProperty	(Ljava/lang/String;Ljava/lang/String;)V
    //   122: aload 7
    //   124: iconst_1
    //   125: invokevirtual 87	java/net/HttpURLConnection:setInstanceFollowRedirects	(Z)V
    //   128: aconst_null
    //   129: astore 4
    //   131: iload_0
    //   132: iconst_2
    //   133: if_icmpeq +8 -> 141
    //   136: iload_0
    //   137: iconst_3
    //   138: if_icmpne +400 -> 538
    //   141: iload_0
    //   142: iconst_2
    //   143: if_icmpne +206 -> 349
    //   146: aload 7
    //   148: ldc 89
    //   150: ldc 91
    //   152: invokevirtual 80	java/net/HttpURLConnection:setRequestProperty	(Ljava/lang/String;Ljava/lang/String;)V
    //   155: aload_2
    //   156: ifnull +784 -> 940
    //   159: aload_2
    //   160: invokeinterface 97 1 0
    //   165: ifle +775 -> 940
    //   168: new 99	java/io/ByteArrayOutputStream
    //   171: dup
    //   172: invokespecial 100	java/io/ByteArrayOutputStream:<init>	()V
    //   175: astore_1
    //   176: aload_2
    //   177: invokeinterface 104 1 0
    //   182: astore 4
    //   184: aload 4
    //   186: invokeinterface 107 1 0
    //   191: anewarray 109	java/lang/String
    //   194: astore 5
    //   196: aload 4
    //   198: aload 5
    //   200: invokeinterface 113 2 0
    //   205: pop
    //   206: invokestatic 118	com/alibaba/mtl/log/e/g:a	()Lcom/alibaba/mtl/log/e/g;
    //   209: aload 5
    //   211: iconst_1
    //   212: invokevirtual 121	com/alibaba/mtl/log/e/g:a	([Ljava/lang/String;Z)[Ljava/lang/String;
    //   215: astore 4
    //   217: aload 4
    //   219: arraylength
    //   220: istore 10
    //   222: iconst_0
    //   223: istore 9
    //   225: iload 9
    //   227: iload 10
    //   229: if_icmpge +267 -> 496
    //   232: aload 4
    //   234: iload 9
    //   236: aaload
    //   237: astore 5
    //   239: iload_0
    //   240: iconst_2
    //   241: if_icmpne +135 -> 376
    //   244: aload_2
    //   245: aload 5
    //   247: invokeinterface 125 2 0
    //   252: checkcast 127	[B
    //   255: checkcast 127	[B
    //   258: astore 8
    //   260: aload 8
    //   262: ifnull +44 -> 306
    //   265: aload_1
    //   266: ldc -127
    //   268: iconst_2
    //   269: anewarray 4	java/lang/Object
    //   272: dup
    //   273: iconst_0
    //   274: aload 5
    //   276: aastore
    //   277: dup
    //   278: iconst_1
    //   279: aload 5
    //   281: aastore
    //   282: invokestatic 133	java/lang/String:format	(Ljava/lang/String;[Ljava/lang/Object;)Ljava/lang/String;
    //   285: invokevirtual 137	java/lang/String:getBytes	()[B
    //   288: invokevirtual 141	java/io/ByteArrayOutputStream:write	([B)V
    //   291: aload_1
    //   292: aload 8
    //   294: invokevirtual 141	java/io/ByteArrayOutputStream:write	([B)V
    //   297: aload_1
    //   298: ldc -113
    //   300: invokevirtual 137	java/lang/String:getBytes	()[B
    //   303: invokevirtual 141	java/io/ByteArrayOutputStream:write	([B)V
    //   306: iload 9
    //   308: iconst_1
    //   309: iadd
    //   310: istore 9
    //   312: goto -87 -> 225
    //   315: astore_1
    //   316: aload_1
    //   317: invokevirtual 146	java/net/MalformedURLException:printStackTrace	()V
    //   320: aload 6
    //   322: areturn
    //   323: astore_1
    //   324: aload_1
    //   325: invokevirtual 147	java/io/IOException:printStackTrace	()V
    //   328: aload 6
    //   330: areturn
    //   331: aload 7
    //   333: ldc -107
    //   335: invokevirtual 61	java/net/HttpURLConnection:setRequestMethod	(Ljava/lang/String;)V
    //   338: goto -259 -> 79
    //   341: astore_1
    //   342: aload_1
    //   343: invokevirtual 150	java/net/ProtocolException:printStackTrace	()V
    //   346: aload 6
    //   348: areturn
    //   349: iload_0
    //   350: iconst_3
    //   351: if_icmpne -196 -> 155
    //   354: aload 7
    //   356: ldc 89
    //   358: ldc -104
    //   360: invokevirtual 80	java/net/HttpURLConnection:setRequestProperty	(Ljava/lang/String;Ljava/lang/String;)V
    //   363: goto -208 -> 155
    //   366: astore 5
    //   368: aload 5
    //   370: invokevirtual 147	java/io/IOException:printStackTrace	()V
    //   373: goto -67 -> 306
    //   376: iload_0
    //   377: iconst_3
    //   378: if_icmpne -72 -> 306
    //   381: aload_2
    //   382: aload 5
    //   384: invokeinterface 125 2 0
    //   389: checkcast 109	java/lang/String
    //   392: astore 8
    //   394: aload_1
    //   395: invokevirtual 153	java/io/ByteArrayOutputStream:size	()I
    //   398: ifle +53 -> 451
    //   401: aload_1
    //   402: new 155	java/lang/StringBuilder
    //   405: dup
    //   406: invokespecial 156	java/lang/StringBuilder:<init>	()V
    //   409: ldc -98
    //   411: invokevirtual 162	java/lang/StringBuilder:append	(Ljava/lang/String;)Ljava/lang/StringBuilder;
    //   414: aload 5
    //   416: invokevirtual 162	java/lang/StringBuilder:append	(Ljava/lang/String;)Ljava/lang/StringBuilder;
    //   419: ldc -92
    //   421: invokevirtual 162	java/lang/StringBuilder:append	(Ljava/lang/String;)Ljava/lang/StringBuilder;
    //   424: aload 8
    //   426: invokevirtual 162	java/lang/StringBuilder:append	(Ljava/lang/String;)Ljava/lang/StringBuilder;
    //   429: invokevirtual 168	java/lang/StringBuilder:toString	()Ljava/lang/String;
    //   432: invokevirtual 137	java/lang/String:getBytes	()[B
    //   435: invokevirtual 141	java/io/ByteArrayOutputStream:write	([B)V
    //   438: goto -132 -> 306
    //   441: astore 5
    //   443: aload 5
    //   445: invokevirtual 147	java/io/IOException:printStackTrace	()V
    //   448: goto -142 -> 306
    //   451: aload_1
    //   452: new 155	java/lang/StringBuilder
    //   455: dup
    //   456: invokespecial 156	java/lang/StringBuilder:<init>	()V
    //   459: aload 5
    //   461: invokevirtual 162	java/lang/StringBuilder:append	(Ljava/lang/String;)Ljava/lang/StringBuilder;
    //   464: ldc -92
    //   466: invokevirtual 162	java/lang/StringBuilder:append	(Ljava/lang/String;)Ljava/lang/StringBuilder;
    //   469: aload 8
    //   471: invokevirtual 162	java/lang/StringBuilder:append	(Ljava/lang/String;)Ljava/lang/StringBuilder;
    //   474: invokevirtual 168	java/lang/StringBuilder:toString	()Ljava/lang/String;
    //   477: invokevirtual 137	java/lang/String:getBytes	()[B
    //   480: invokevirtual 141	java/io/ByteArrayOutputStream:write	([B)V
    //   483: goto -177 -> 306
    //   486: astore 5
    //   488: aload 5
    //   490: invokevirtual 147	java/io/IOException:printStackTrace	()V
    //   493: goto -187 -> 306
    //   496: iload_0
    //   497: iconst_2
    //   498: if_icmpne +12 -> 510
    //   501: aload_1
    //   502: ldc -86
    //   504: invokevirtual 137	java/lang/String:getBytes	()[B
    //   507: invokevirtual 141	java/io/ByteArrayOutputStream:write	([B)V
    //   510: aload_1
    //   511: invokevirtual 173	java/io/ByteArrayOutputStream:toByteArray	()[B
    //   514: astore_1
    //   515: aload_1
    //   516: ifnull +418 -> 934
    //   519: aload_1
    //   520: arraylength
    //   521: istore 9
    //   523: aload 7
    //   525: ldc -81
    //   527: iload 9
    //   529: invokestatic 179	java/lang/String:valueOf	(I)Ljava/lang/String;
    //   532: invokevirtual 80	java/net/HttpURLConnection:setRequestProperty	(Ljava/lang/String;Ljava/lang/String;)V
    //   535: aload_1
    //   536: astore 4
    //   538: aconst_null
    //   539: astore_2
    //   540: aconst_null
    //   541: astore 5
    //   543: aload 7
    //   545: invokevirtual 182	java/net/HttpURLConnection:connect	()V
    //   548: iload_0
    //   549: iconst_2
    //   550: if_icmpeq +11 -> 561
    //   553: aload 5
    //   555: astore_1
    //   556: iload_0
    //   557: iconst_3
    //   558: if_icmpne +43 -> 601
    //   561: aload 5
    //   563: astore_1
    //   564: aload 4
    //   566: ifnull +35 -> 601
    //   569: aload 5
    //   571: astore_1
    //   572: aload 4
    //   574: arraylength
    //   575: ifle +26 -> 601
    //   578: new 184	java/io/DataOutputStream
    //   581: dup
    //   582: aload 7
    //   584: invokevirtual 188	java/net/HttpURLConnection:getOutputStream	()Ljava/io/OutputStream;
    //   587: invokespecial 191	java/io/DataOutputStream:<init>	(Ljava/io/OutputStream;)V
    //   590: astore_1
    //   591: aload_1
    //   592: aload 4
    //   594: invokevirtual 192	java/io/DataOutputStream:write	([B)V
    //   597: aload_1
    //   598: invokevirtual 195	java/io/DataOutputStream:flush	()V
    //   601: aload_1
    //   602: ifnull +7 -> 609
    //   605: aload_1
    //   606: invokevirtual 197	java/io/DataOutputStream:close	()V
    //   609: aload 6
    //   611: aload 7
    //   613: invokevirtual 200	java/net/HttpURLConnection:getResponseCode	()I
    //   616: putfield 204	com/alibaba/mtl/log/e/e$a:E	I
    //   619: aconst_null
    //   620: astore 5
    //   622: aconst_null
    //   623: astore_1
    //   624: new 99	java/io/ByteArrayOutputStream
    //   627: dup
    //   628: invokespecial 100	java/io/ByteArrayOutputStream:<init>	()V
    //   631: astore 8
    //   633: iload_3
    //   634: ifeq +190 -> 824
    //   637: aload_1
    //   638: astore 4
    //   640: aload 5
    //   642: astore_2
    //   643: ldc -50
    //   645: aload 7
    //   647: invokevirtual 209	java/net/HttpURLConnection:getContentEncoding	()Ljava/lang/String;
    //   650: invokevirtual 213	java/lang/String:equals	(Ljava/lang/Object;)Z
    //   653: ifeq +171 -> 824
    //   656: aload_1
    //   657: astore 4
    //   659: aload 5
    //   661: astore_2
    //   662: new 215	java/util/zip/GZIPInputStream
    //   665: dup
    //   666: aload 7
    //   668: invokevirtual 219	java/net/HttpURLConnection:getInputStream	()Ljava/io/InputStream;
    //   671: invokespecial 222	java/util/zip/GZIPInputStream:<init>	(Ljava/io/InputStream;)V
    //   674: astore_1
    //   675: aload_1
    //   676: astore 4
    //   678: aload_1
    //   679: astore_2
    //   680: invokestatic 226	java/lang/System:currentTimeMillis	()J
    //   683: pop2
    //   684: aload_1
    //   685: astore 4
    //   687: aload_1
    //   688: astore_2
    //   689: sipush 2048
    //   692: newarray <illegal type>
    //   694: astore 5
    //   696: aload_1
    //   697: astore 4
    //   699: aload_1
    //   700: astore_2
    //   701: aload_1
    //   702: aload 5
    //   704: iconst_0
    //   705: sipush 2048
    //   708: invokevirtual 232	java/io/InputStream:read	([BII)I
    //   711: istore_0
    //   712: iload_0
    //   713: iconst_m1
    //   714: if_icmpeq +132 -> 846
    //   717: aload_1
    //   718: astore 4
    //   720: aload_1
    //   721: astore_2
    //   722: aload 8
    //   724: aload 5
    //   726: iconst_0
    //   727: iload_0
    //   728: invokevirtual 235	java/io/ByteArrayOutputStream:write	([BII)V
    //   731: goto -35 -> 696
    //   734: astore_1
    //   735: aload 4
    //   737: astore_2
    //   738: aload_1
    //   739: invokevirtual 147	java/io/IOException:printStackTrace	()V
    //   742: aload 4
    //   744: ifnull +8 -> 752
    //   747: aload 4
    //   749: invokevirtual 236	java/io/InputStream:close	()V
    //   752: aload 6
    //   754: areturn
    //   755: astore_2
    //   756: aload_2
    //   757: invokevirtual 147	java/io/IOException:printStackTrace	()V
    //   760: goto -250 -> 510
    //   763: astore_1
    //   764: aload_1
    //   765: invokevirtual 147	java/io/IOException:printStackTrace	()V
    //   768: goto -159 -> 609
    //   771: astore_2
    //   772: aconst_null
    //   773: astore_1
    //   774: aload_2
    //   775: invokevirtual 237	java/lang/Exception:printStackTrace	()V
    //   778: aload_1
    //   779: ifnull +7 -> 786
    //   782: aload_1
    //   783: invokevirtual 197	java/io/DataOutputStream:close	()V
    //   786: aload 6
    //   788: areturn
    //   789: astore_1
    //   790: aload_1
    //   791: invokevirtual 147	java/io/IOException:printStackTrace	()V
    //   794: goto -8 -> 786
    //   797: astore_1
    //   798: aload_2
    //   799: ifnull +7 -> 806
    //   802: aload_2
    //   803: invokevirtual 197	java/io/DataOutputStream:close	()V
    //   806: aload_1
    //   807: athrow
    //   808: astore_2
    //   809: aload_2
    //   810: invokevirtual 147	java/io/IOException:printStackTrace	()V
    //   813: goto -7 -> 806
    //   816: astore_1
    //   817: aload_1
    //   818: invokevirtual 147	java/io/IOException:printStackTrace	()V
    //   821: goto -202 -> 619
    //   824: aload_1
    //   825: astore 4
    //   827: aload 5
    //   829: astore_2
    //   830: new 239	java/io/DataInputStream
    //   833: dup
    //   834: aload 7
    //   836: invokevirtual 219	java/net/HttpURLConnection:getInputStream	()Ljava/io/InputStream;
    //   839: invokespecial 240	java/io/DataInputStream:<init>	(Ljava/io/InputStream;)V
    //   842: astore_1
    //   843: goto -168 -> 675
    //   846: aload_1
    //   847: ifnull +7 -> 854
    //   850: aload_1
    //   851: invokevirtual 236	java/io/InputStream:close	()V
    //   854: aload 8
    //   856: invokevirtual 153	java/io/ByteArrayOutputStream:size	()I
    //   859: ifle +13 -> 872
    //   862: aload 6
    //   864: aload 8
    //   866: invokevirtual 173	java/io/ByteArrayOutputStream:toByteArray	()[B
    //   869: putfield 243	com/alibaba/mtl/log/e/e$a:e	[B
    //   872: aload 6
    //   874: areturn
    //   875: astore_1
    //   876: aload_1
    //   877: invokevirtual 237	java/lang/Exception:printStackTrace	()V
    //   880: goto -26 -> 854
    //   883: astore_1
    //   884: aload_1
    //   885: invokevirtual 237	java/lang/Exception:printStackTrace	()V
    //   888: goto -136 -> 752
    //   891: astore_1
    //   892: aload_2
    //   893: ifnull +7 -> 900
    //   896: aload_2
    //   897: invokevirtual 236	java/io/InputStream:close	()V
    //   900: aload_1
    //   901: athrow
    //   902: astore_2
    //   903: aload_2
    //   904: invokevirtual 237	java/lang/Exception:printStackTrace	()V
    //   907: goto -7 -> 900
    //   910: astore 4
    //   912: aload_1
    //   913: astore_2
    //   914: aload 4
    //   916: astore_1
    //   917: goto -119 -> 798
    //   920: astore 4
    //   922: aload_1
    //   923: astore_2
    //   924: aload 4
    //   926: astore_1
    //   927: goto -129 -> 798
    //   930: astore_2
    //   931: goto -157 -> 774
    //   934: iconst_0
    //   935: istore 9
    //   937: goto -414 -> 523
    //   940: aconst_null
    //   941: astore_1
    //   942: goto -427 -> 515
    // Local variable table:
    //   start	length	slot	name	signature
    //   0	945	0	paramInt	int
    //   0	945	1	paramString	String
    //   0	945	2	paramMap	java.util.Map<String, Object>
    //   0	945	3	paramBoolean	boolean
    //   129	697	4	localObject1	Object
    //   910	5	4	localObject2	Object
    //   920	5	4	localObject3	Object
    //   194	86	5	arrayOfString	String[]
    //   366	49	5	localIOException1	java.io.IOException
    //   441	19	5	localIOException2	java.io.IOException
    //   486	3	5	localIOException3	java.io.IOException
    //   541	287	5	arrayOfByte	byte[]
    //   7	866	6	locala	a
    //   33	802	7	localHttpURLConnection	java.net.HttpURLConnection
    //   258	607	8	localObject4	Object
    //   223	713	9	i	int
    //   220	10	10	j	int
    // Exception table:
    //   from	to	target	type
    //   19	35	315	java/net/MalformedURLException
    //   19	35	323	java/io/IOException
    //   72	79	341	java/net/ProtocolException
    //   331	338	341	java/net/ProtocolException
    //   265	306	366	java/io/IOException
    //   401	438	441	java/io/IOException
    //   451	483	486	java/io/IOException
    //   643	656	734	java/io/IOException
    //   662	675	734	java/io/IOException
    //   680	684	734	java/io/IOException
    //   689	696	734	java/io/IOException
    //   701	712	734	java/io/IOException
    //   722	731	734	java/io/IOException
    //   830	843	734	java/io/IOException
    //   501	510	755	java/io/IOException
    //   605	609	763	java/io/IOException
    //   543	548	771	java/lang/Exception
    //   572	591	771	java/lang/Exception
    //   782	786	789	java/io/IOException
    //   543	548	797	finally
    //   572	591	797	finally
    //   802	806	808	java/io/IOException
    //   609	619	816	java/io/IOException
    //   850	854	875	java/lang/Exception
    //   747	752	883	java/lang/Exception
    //   643	656	891	finally
    //   662	675	891	finally
    //   680	684	891	finally
    //   689	696	891	finally
    //   701	712	891	finally
    //   722	731	891	finally
    //   738	742	891	finally
    //   830	843	891	finally
    //   896	900	902	java/lang/Exception
    //   591	601	910	finally
    //   774	778	920	finally
    //   591	601	930	java/lang/Exception
  }
  
  public static class a
  {
    public int E = -1;
    public byte[] e = null;
  }
}


/* Location:              E:\apk\xiaoenai2\classes-dex2jar.jar!\com\alibaba\mtl\log\e\e.class
 * Java compiler version: 6 (50.0)
 * JD-Core Version:       0.7.1
 */