package com.tencent.bugly.proguard;

final class x$1
  implements Runnable
{
  x$1(String paramString) {}
  
  /* Error */
  public final void run()
  {
    // Byte code:
    //   0: invokestatic 24	com/tencent/bugly/proguard/x:a	()Ljava/lang/Object;
    //   3: astore_1
    //   4: aload_1
    //   5: monitorenter
    //   6: invokestatic 28	com/tencent/bugly/proguard/x:b	()Ljava/lang/StringBuilder;
    //   9: invokevirtual 34	java/lang/StringBuilder:length	()I
    //   12: istore_3
    //   13: invokestatic 37	com/tencent/bugly/proguard/x:c	()I
    //   16: istore 4
    //   18: iload_3
    //   19: iload 4
    //   21: if_icmpgt +6 -> 27
    //   24: aload_1
    //   25: monitorexit
    //   26: return
    //   27: invokestatic 41	com/tencent/bugly/proguard/x:d	()Lcom/tencent/bugly/proguard/x$a;
    //   30: ifnonnull +54 -> 84
    //   33: new 43	com/tencent/bugly/proguard/x$a
    //   36: dup
    //   37: invokestatic 47	com/tencent/bugly/proguard/x:e	()Ljava/lang/String;
    //   40: invokespecial 49	com/tencent/bugly/proguard/x$a:<init>	(Ljava/lang/String;)V
    //   43: invokestatic 52	com/tencent/bugly/proguard/x:a	(Lcom/tencent/bugly/proguard/x$a;)Lcom/tencent/bugly/proguard/x$a;
    //   46: pop
    //   47: invokestatic 41	com/tencent/bugly/proguard/x:d	()Lcom/tencent/bugly/proguard/x$a;
    //   50: invokestatic 55	com/tencent/bugly/proguard/x$a:d	(Lcom/tencent/bugly/proguard/x$a;)Z
    //   53: ifeq +68 -> 121
    //   56: invokestatic 41	com/tencent/bugly/proguard/x:d	()Lcom/tencent/bugly/proguard/x$a;
    //   59: invokestatic 28	com/tencent/bugly/proguard/x:b	()Ljava/lang/StringBuilder;
    //   62: invokevirtual 58	java/lang/StringBuilder:toString	()Ljava/lang/String;
    //   65: invokevirtual 61	com/tencent/bugly/proguard/x$a:a	(Ljava/lang/String;)Z
    //   68: pop
    //   69: invokestatic 28	com/tencent/bugly/proguard/x:b	()Ljava/lang/StringBuilder;
    //   72: iconst_0
    //   73: invokevirtual 65	java/lang/StringBuilder:setLength	(I)V
    //   76: aload_1
    //   77: monitorexit
    //   78: return
    //   79: astore_2
    //   80: aload_1
    //   81: monitorexit
    //   82: aload_2
    //   83: athrow
    //   84: invokestatic 41	com/tencent/bugly/proguard/x:d	()Lcom/tencent/bugly/proguard/x$a;
    //   87: invokestatic 68	com/tencent/bugly/proguard/x$a:a	(Lcom/tencent/bugly/proguard/x$a;)Ljava/io/File;
    //   90: invokevirtual 73	java/io/File:length	()J
    //   93: invokestatic 28	com/tencent/bugly/proguard/x:b	()Ljava/lang/StringBuilder;
    //   96: invokevirtual 34	java/lang/StringBuilder:length	()I
    //   99: i2l
    //   100: ladd
    //   101: invokestatic 41	com/tencent/bugly/proguard/x:d	()Lcom/tencent/bugly/proguard/x$a;
    //   104: invokestatic 76	com/tencent/bugly/proguard/x$a:b	(Lcom/tencent/bugly/proguard/x$a;)J
    //   107: lcmp
    //   108: ifle -61 -> 47
    //   111: invokestatic 41	com/tencent/bugly/proguard/x:d	()Lcom/tencent/bugly/proguard/x$a;
    //   114: invokestatic 78	com/tencent/bugly/proguard/x$a:c	(Lcom/tencent/bugly/proguard/x$a;)Z
    //   117: pop
    //   118: goto -71 -> 47
    //   121: invokestatic 28	com/tencent/bugly/proguard/x:b	()Ljava/lang/StringBuilder;
    //   124: iconst_0
    //   125: invokevirtual 65	java/lang/StringBuilder:setLength	(I)V
    //   128: invokestatic 28	com/tencent/bugly/proguard/x:b	()Ljava/lang/StringBuilder;
    //   131: aload_0
    //   132: getfield 12	com/tencent/bugly/proguard/x$1:a	Ljava/lang/String;
    //   135: invokevirtual 82	java/lang/StringBuilder:append	(Ljava/lang/String;)Ljava/lang/StringBuilder;
    //   138: pop
    //   139: goto -63 -> 76
    //   142: astore_2
    //   143: goto -67 -> 76
    // Local variable table:
    //   start	length	slot	name	signature
    //   0	146	0	this	1
    //   79	4	2	localObject2	Object
    //   142	1	2	localThrowable	Throwable
    //   12	10	3	i	int
    //   16	6	4	j	int
    // Exception table:
    //   from	to	target	type
    //   6	18	79	finally
    //   24	26	79	finally
    //   27	47	79	finally
    //   47	76	79	finally
    //   76	78	79	finally
    //   84	118	79	finally
    //   121	139	79	finally
    //   6	18	142	java/lang/Throwable
    //   27	47	142	java/lang/Throwable
    //   47	76	142	java/lang/Throwable
    //   84	118	142	java/lang/Throwable
    //   121	139	142	java/lang/Throwable
  }
}


/* Location:              E:\apk\xiaoenai2\classes2-dex2jar.jar!\com\tencent\bugly\proguard\x$1.class
 * Java compiler version: 6 (50.0)
 * JD-Core Version:       0.7.1
 */