package com.tencent.bugly.proguard;

import android.content.Context;
import com.tencent.bugly.BuglyStrategy.a;
import com.tencent.bugly.crashreport.crash.b;

public final class y
{
  private Context a;
  private b b;
  private com.tencent.bugly.crashreport.common.strategy.a c;
  private com.tencent.bugly.crashreport.common.info.a d;
  
  public y(Context paramContext, b paramb, com.tencent.bugly.crashreport.common.strategy.a parama, com.tencent.bugly.crashreport.common.info.a parama1, BuglyStrategy.a parama2)
  {
    this.a = paramContext;
    this.b = paramb;
    this.c = parama;
    this.d = parama1;
  }
  
  /* Error */
  public final void a(Thread paramThread, int paramInt, String paramString1, String paramString2, String paramString3)
  {
    // Byte code:
    //   0: ldc 33
    //   2: iconst_0
    //   3: anewarray 4	java/lang/Object
    //   6: invokestatic 39	com/tencent/bugly/proguard/w:e	(Ljava/lang/String;[Ljava/lang/Object;)Z
    //   9: pop
    //   10: aload_0
    //   11: getfield 23	com/tencent/bugly/proguard/y:c	Lcom/tencent/bugly/crashreport/common/strategy/a;
    //   14: invokevirtual 44	com/tencent/bugly/crashreport/common/strategy/a:c	()Lcom/tencent/bugly/crashreport/common/strategy/StrategyBean;
    //   17: pop
    //   18: aload_0
    //   19: getfield 23	com/tencent/bugly/proguard/y:c	Lcom/tencent/bugly/crashreport/common/strategy/a;
    //   22: invokevirtual 47	com/tencent/bugly/crashreport/common/strategy/a:b	()Z
    //   25: ifne +56 -> 81
    //   28: ldc 49
    //   30: iconst_0
    //   31: anewarray 4	java/lang/Object
    //   34: invokestatic 39	com/tencent/bugly/proguard/w:e	(Ljava/lang/String;[Ljava/lang/Object;)Z
    //   37: pop
    //   38: iconst_0
    //   39: istore 10
    //   41: aload_0
    //   42: getfield 23	com/tencent/bugly/proguard/y:c	Lcom/tencent/bugly/crashreport/common/strategy/a;
    //   45: invokevirtual 47	com/tencent/bugly/crashreport/common/strategy/a:b	()Z
    //   48: istore 12
    //   50: iload 12
    //   52: ifne +29 -> 81
    //   55: ldc2_w 50
    //   58: invokestatic 57	java/lang/Thread:sleep	(J)V
    //   61: iload 10
    //   63: sipush 500
    //   66: iadd
    //   67: istore 11
    //   69: iload 11
    //   71: istore 10
    //   73: iload 11
    //   75: sipush 5000
    //   78: if_icmplt -37 -> 41
    //   81: aload_0
    //   82: getfield 23	com/tencent/bugly/proguard/y:c	Lcom/tencent/bugly/crashreport/common/strategy/a;
    //   85: invokevirtual 47	com/tencent/bugly/crashreport/common/strategy/a:b	()Z
    //   88: ifne +13 -> 101
    //   91: ldc 59
    //   93: iconst_0
    //   94: anewarray 4	java/lang/Object
    //   97: invokestatic 61	com/tencent/bugly/proguard/w:d	(Ljava/lang/String;[Ljava/lang/Object;)Z
    //   100: pop
    //   101: aload_0
    //   102: getfield 23	com/tencent/bugly/proguard/y:c	Lcom/tencent/bugly/crashreport/common/strategy/a;
    //   105: invokevirtual 44	com/tencent/bugly/crashreport/common/strategy/a:c	()Lcom/tencent/bugly/crashreport/common/strategy/StrategyBean;
    //   108: astore 6
    //   110: aload 6
    //   112: getfield 66	com/tencent/bugly/crashreport/common/strategy/StrategyBean:d	Z
    //   115: ifne +118 -> 233
    //   118: aload_0
    //   119: getfield 23	com/tencent/bugly/proguard/y:c	Lcom/tencent/bugly/crashreport/common/strategy/a;
    //   122: invokevirtual 47	com/tencent/bugly/crashreport/common/strategy/a:b	()Z
    //   125: ifeq +108 -> 233
    //   128: ldc 68
    //   130: iconst_0
    //   131: anewarray 4	java/lang/Object
    //   134: invokestatic 39	com/tencent/bugly/proguard/w:e	(Ljava/lang/String;[Ljava/lang/Object;)Z
    //   137: pop
    //   138: ldc 70
    //   140: invokestatic 76	com/tencent/bugly/proguard/a:n	()Ljava/lang/String;
    //   143: aload_0
    //   144: getfield 25	com/tencent/bugly/proguard/y:d	Lcom/tencent/bugly/crashreport/common/info/a;
    //   147: getfield 81	com/tencent/bugly/crashreport/common/info/a:d	Ljava/lang/String;
    //   150: aload_1
    //   151: new 83	java/lang/StringBuilder
    //   154: dup
    //   155: invokespecial 84	java/lang/StringBuilder:<init>	()V
    //   158: aload_3
    //   159: invokevirtual 88	java/lang/StringBuilder:append	(Ljava/lang/String;)Ljava/lang/StringBuilder;
    //   162: ldc 90
    //   164: invokevirtual 88	java/lang/StringBuilder:append	(Ljava/lang/String;)Ljava/lang/StringBuilder;
    //   167: aload 4
    //   169: invokevirtual 88	java/lang/StringBuilder:append	(Ljava/lang/String;)Ljava/lang/StringBuilder;
    //   172: ldc 90
    //   174: invokevirtual 88	java/lang/StringBuilder:append	(Ljava/lang/String;)Ljava/lang/StringBuilder;
    //   177: aload 5
    //   179: invokevirtual 88	java/lang/StringBuilder:append	(Ljava/lang/String;)Ljava/lang/StringBuilder;
    //   182: invokevirtual 93	java/lang/StringBuilder:toString	()Ljava/lang/String;
    //   185: aconst_null
    //   186: invokestatic 98	com/tencent/bugly/crashreport/crash/b:a	(Ljava/lang/String;Ljava/lang/String;Ljava/lang/String;Ljava/lang/Thread;Ljava/lang/String;Lcom/tencent/bugly/crashreport/crash/CrashDetailBean;)V
    //   189: ldc 100
    //   191: iconst_0
    //   192: anewarray 4	java/lang/Object
    //   195: invokestatic 39	com/tencent/bugly/proguard/w:e	(Ljava/lang/String;[Ljava/lang/Object;)Z
    //   198: pop
    //   199: return
    //   200: astore 6
    //   202: aload 6
    //   204: invokevirtual 103	java/lang/InterruptedException:printStackTrace	()V
    //   207: goto -146 -> 61
    //   210: astore_1
    //   211: aload_1
    //   212: invokestatic 106	com/tencent/bugly/proguard/w:a	(Ljava/lang/Throwable;)Z
    //   215: ifne +7 -> 222
    //   218: aload_1
    //   219: invokevirtual 107	java/lang/Throwable:printStackTrace	()V
    //   222: ldc 100
    //   224: iconst_0
    //   225: anewarray 4	java/lang/Object
    //   228: invokestatic 39	com/tencent/bugly/proguard/w:e	(Ljava/lang/String;[Ljava/lang/Object;)Z
    //   231: pop
    //   232: return
    //   233: aload 6
    //   235: getfield 110	com/tencent/bugly/crashreport/common/strategy/StrategyBean:h	Z
    //   238: ifne +24 -> 262
    //   241: ldc 112
    //   243: iconst_0
    //   244: anewarray 4	java/lang/Object
    //   247: invokestatic 39	com/tencent/bugly/proguard/w:e	(Ljava/lang/String;[Ljava/lang/Object;)Z
    //   250: pop
    //   251: ldc 100
    //   253: iconst_0
    //   254: anewarray 4	java/lang/Object
    //   257: invokestatic 39	com/tencent/bugly/proguard/w:e	(Ljava/lang/String;[Ljava/lang/Object;)Z
    //   260: pop
    //   261: return
    //   262: new 114	com/tencent/bugly/crashreport/crash/CrashDetailBean
    //   265: dup
    //   266: invokespecial 115	com/tencent/bugly/crashreport/crash/CrashDetailBean:<init>	()V
    //   269: astore 8
    //   271: aload 8
    //   273: invokestatic 119	com/tencent/bugly/proguard/a:i	()J
    //   276: putfield 123	com/tencent/bugly/crashreport/crash/CrashDetailBean:B	J
    //   279: aload 8
    //   281: invokestatic 126	com/tencent/bugly/proguard/a:g	()J
    //   284: putfield 129	com/tencent/bugly/crashreport/crash/CrashDetailBean:C	J
    //   287: aload 8
    //   289: invokestatic 132	com/tencent/bugly/proguard/a:k	()J
    //   292: putfield 135	com/tencent/bugly/crashreport/crash/CrashDetailBean:D	J
    //   295: aload 8
    //   297: aload_0
    //   298: getfield 25	com/tencent/bugly/proguard/y:d	Lcom/tencent/bugly/crashreport/common/info/a;
    //   301: invokevirtual 138	com/tencent/bugly/crashreport/common/info/a:o	()J
    //   304: putfield 141	com/tencent/bugly/crashreport/crash/CrashDetailBean:E	J
    //   307: aload 8
    //   309: aload_0
    //   310: getfield 25	com/tencent/bugly/proguard/y:d	Lcom/tencent/bugly/crashreport/common/info/a;
    //   313: invokevirtual 143	com/tencent/bugly/crashreport/common/info/a:n	()J
    //   316: putfield 146	com/tencent/bugly/crashreport/crash/CrashDetailBean:F	J
    //   319: aload 8
    //   321: aload_0
    //   322: getfield 25	com/tencent/bugly/proguard/y:d	Lcom/tencent/bugly/crashreport/common/info/a;
    //   325: invokevirtual 149	com/tencent/bugly/crashreport/common/info/a:p	()J
    //   328: putfield 152	com/tencent/bugly/crashreport/crash/CrashDetailBean:G	J
    //   331: aload 8
    //   333: aload_0
    //   334: getfield 19	com/tencent/bugly/proguard/y:a	Landroid/content/Context;
    //   337: getstatic 157	com/tencent/bugly/crashreport/crash/c:d	I
    //   340: aconst_null
    //   341: invokestatic 160	com/tencent/bugly/proguard/a:a	(Landroid/content/Context;ILjava/lang/String;)Ljava/lang/String;
    //   344: putfield 163	com/tencent/bugly/crashreport/crash/CrashDetailBean:w	Ljava/lang/String;
    //   347: aload 8
    //   349: iconst_0
    //   350: invokestatic 168	com/tencent/bugly/proguard/x:a	(Z)[B
    //   353: putfield 172	com/tencent/bugly/crashreport/crash/CrashDetailBean:x	[B
    //   356: aload 8
    //   358: iload_2
    //   359: putfield 174	com/tencent/bugly/crashreport/crash/CrashDetailBean:b	I
    //   362: aload 8
    //   364: aload_0
    //   365: getfield 25	com/tencent/bugly/proguard/y:d	Lcom/tencent/bugly/crashreport/common/info/a;
    //   368: invokevirtual 176	com/tencent/bugly/crashreport/common/info/a:g	()Ljava/lang/String;
    //   371: putfield 178	com/tencent/bugly/crashreport/crash/CrashDetailBean:e	Ljava/lang/String;
    //   374: aload 8
    //   376: aload_0
    //   377: getfield 25	com/tencent/bugly/proguard/y:d	Lcom/tencent/bugly/crashreport/common/info/a;
    //   380: getfield 180	com/tencent/bugly/crashreport/common/info/a:i	Ljava/lang/String;
    //   383: putfield 183	com/tencent/bugly/crashreport/crash/CrashDetailBean:f	Ljava/lang/String;
    //   386: aload 8
    //   388: aload_0
    //   389: getfield 25	com/tencent/bugly/proguard/y:d	Lcom/tencent/bugly/crashreport/common/info/a;
    //   392: invokevirtual 186	com/tencent/bugly/crashreport/common/info/a:t	()Ljava/lang/String;
    //   395: putfield 188	com/tencent/bugly/crashreport/crash/CrashDetailBean:g	Ljava/lang/String;
    //   398: aload 8
    //   400: aload_0
    //   401: getfield 25	com/tencent/bugly/proguard/y:d	Lcom/tencent/bugly/crashreport/common/info/a;
    //   404: invokevirtual 190	com/tencent/bugly/crashreport/common/info/a:f	()Ljava/lang/String;
    //   407: putfield 193	com/tencent/bugly/crashreport/crash/CrashDetailBean:m	Ljava/lang/String;
    //   410: aload 8
    //   412: new 83	java/lang/StringBuilder
    //   415: dup
    //   416: invokespecial 84	java/lang/StringBuilder:<init>	()V
    //   419: aload_3
    //   420: invokevirtual 88	java/lang/StringBuilder:append	(Ljava/lang/String;)Ljava/lang/StringBuilder;
    //   423: invokevirtual 93	java/lang/StringBuilder:toString	()Ljava/lang/String;
    //   426: putfield 195	com/tencent/bugly/crashreport/crash/CrashDetailBean:n	Ljava/lang/String;
    //   429: aload 8
    //   431: new 83	java/lang/StringBuilder
    //   434: dup
    //   435: invokespecial 84	java/lang/StringBuilder:<init>	()V
    //   438: aload 4
    //   440: invokevirtual 88	java/lang/StringBuilder:append	(Ljava/lang/String;)Ljava/lang/StringBuilder;
    //   443: invokevirtual 93	java/lang/StringBuilder:toString	()Ljava/lang/String;
    //   446: putfield 197	com/tencent/bugly/crashreport/crash/CrashDetailBean:o	Ljava/lang/String;
    //   449: ldc -57
    //   451: astore 7
    //   453: aload 7
    //   455: astore 6
    //   457: aload 5
    //   459: ifnull +37 -> 496
    //   462: aload 5
    //   464: ldc 90
    //   466: invokevirtual 205	java/lang/String:split	(Ljava/lang/String;)[Ljava/lang/String;
    //   469: astore 9
    //   471: aload 7
    //   473: astore 6
    //   475: aload 9
    //   477: ifnull +19 -> 496
    //   480: aload 7
    //   482: astore 6
    //   484: aload 9
    //   486: arraylength
    //   487: ifle +9 -> 496
    //   490: aload 9
    //   492: iconst_0
    //   493: aaload
    //   494: astore 6
    //   496: aload 8
    //   498: aload 6
    //   500: putfield 207	com/tencent/bugly/crashreport/crash/CrashDetailBean:p	Ljava/lang/String;
    //   503: aload 8
    //   505: aload 5
    //   507: putfield 210	com/tencent/bugly/crashreport/crash/CrashDetailBean:q	Ljava/lang/String;
    //   510: aload 8
    //   512: invokestatic 215	java/lang/System:currentTimeMillis	()J
    //   515: putfield 218	com/tencent/bugly/crashreport/crash/CrashDetailBean:r	J
    //   518: aload 8
    //   520: aload 8
    //   522: getfield 210	com/tencent/bugly/crashreport/crash/CrashDetailBean:q	Ljava/lang/String;
    //   525: invokevirtual 222	java/lang/String:getBytes	()[B
    //   528: invokestatic 225	com/tencent/bugly/proguard/a:b	([B)Ljava/lang/String;
    //   531: putfield 228	com/tencent/bugly/crashreport/crash/CrashDetailBean:u	Ljava/lang/String;
    //   534: aload 8
    //   536: getstatic 230	com/tencent/bugly/crashreport/crash/c:e	I
    //   539: iconst_0
    //   540: invokestatic 233	com/tencent/bugly/proguard/a:a	(IZ)Ljava/util/Map;
    //   543: putfield 237	com/tencent/bugly/crashreport/crash/CrashDetailBean:y	Ljava/util/Map;
    //   546: aload 8
    //   548: aload_0
    //   549: getfield 25	com/tencent/bugly/proguard/y:d	Lcom/tencent/bugly/crashreport/common/info/a;
    //   552: getfield 81	com/tencent/bugly/crashreport/common/info/a:d	Ljava/lang/String;
    //   555: putfield 240	com/tencent/bugly/crashreport/crash/CrashDetailBean:z	Ljava/lang/String;
    //   558: aload 8
    //   560: new 83	java/lang/StringBuilder
    //   563: dup
    //   564: invokespecial 84	java/lang/StringBuilder:<init>	()V
    //   567: aload_1
    //   568: invokevirtual 243	java/lang/Thread:getName	()Ljava/lang/String;
    //   571: invokevirtual 88	java/lang/StringBuilder:append	(Ljava/lang/String;)Ljava/lang/StringBuilder;
    //   574: ldc -11
    //   576: invokevirtual 88	java/lang/StringBuilder:append	(Ljava/lang/String;)Ljava/lang/StringBuilder;
    //   579: aload_1
    //   580: invokevirtual 248	java/lang/Thread:getId	()J
    //   583: invokevirtual 251	java/lang/StringBuilder:append	(J)Ljava/lang/StringBuilder;
    //   586: ldc -3
    //   588: invokevirtual 88	java/lang/StringBuilder:append	(Ljava/lang/String;)Ljava/lang/StringBuilder;
    //   591: invokevirtual 93	java/lang/StringBuilder:toString	()Ljava/lang/String;
    //   594: putfield 256	com/tencent/bugly/crashreport/crash/CrashDetailBean:A	Ljava/lang/String;
    //   597: aload 8
    //   599: aload_0
    //   600: getfield 25	com/tencent/bugly/proguard/y:d	Lcom/tencent/bugly/crashreport/common/info/a;
    //   603: invokevirtual 259	com/tencent/bugly/crashreport/common/info/a:v	()Ljava/lang/String;
    //   606: putfield 262	com/tencent/bugly/crashreport/crash/CrashDetailBean:H	Ljava/lang/String;
    //   609: aload 8
    //   611: aload_0
    //   612: getfield 25	com/tencent/bugly/proguard/y:d	Lcom/tencent/bugly/crashreport/common/info/a;
    //   615: invokevirtual 266	com/tencent/bugly/crashreport/common/info/a:s	()Ljava/util/Map;
    //   618: putfield 268	com/tencent/bugly/crashreport/crash/CrashDetailBean:h	Ljava/util/Map;
    //   621: aload 8
    //   623: aload_0
    //   624: getfield 25	com/tencent/bugly/proguard/y:d	Lcom/tencent/bugly/crashreport/common/info/a;
    //   627: invokevirtual 270	com/tencent/bugly/crashreport/common/info/a:E	()Ljava/util/Map;
    //   630: putfield 272	com/tencent/bugly/crashreport/crash/CrashDetailBean:i	Ljava/util/Map;
    //   633: aload 8
    //   635: aload_0
    //   636: getfield 25	com/tencent/bugly/proguard/y:d	Lcom/tencent/bugly/crashreport/common/info/a;
    //   639: getfield 274	com/tencent/bugly/crashreport/common/info/a:a	J
    //   642: putfield 277	com/tencent/bugly/crashreport/crash/CrashDetailBean:L	J
    //   645: aload 8
    //   647: aload_0
    //   648: getfield 25	com/tencent/bugly/proguard/y:d	Lcom/tencent/bugly/crashreport/common/info/a;
    //   651: getfield 279	com/tencent/bugly/crashreport/common/info/a:n	Z
    //   654: putfield 282	com/tencent/bugly/crashreport/crash/CrashDetailBean:M	Z
    //   657: aload 8
    //   659: aload_0
    //   660: getfield 25	com/tencent/bugly/proguard/y:d	Lcom/tencent/bugly/crashreport/common/info/a;
    //   663: invokevirtual 285	com/tencent/bugly/crashreport/common/info/a:B	()I
    //   666: putfield 288	com/tencent/bugly/crashreport/crash/CrashDetailBean:O	I
    //   669: aload 8
    //   671: aload_0
    //   672: getfield 25	com/tencent/bugly/proguard/y:d	Lcom/tencent/bugly/crashreport/common/info/a;
    //   675: invokevirtual 290	com/tencent/bugly/crashreport/common/info/a:C	()I
    //   678: putfield 293	com/tencent/bugly/crashreport/crash/CrashDetailBean:P	I
    //   681: aload 8
    //   683: aload_0
    //   684: getfield 25	com/tencent/bugly/proguard/y:d	Lcom/tencent/bugly/crashreport/common/info/a;
    //   687: invokevirtual 295	com/tencent/bugly/crashreport/common/info/a:w	()Ljava/util/Map;
    //   690: putfield 298	com/tencent/bugly/crashreport/crash/CrashDetailBean:Q	Ljava/util/Map;
    //   693: aload 8
    //   695: aload_0
    //   696: getfield 25	com/tencent/bugly/proguard/y:d	Lcom/tencent/bugly/crashreport/common/info/a;
    //   699: invokevirtual 300	com/tencent/bugly/crashreport/common/info/a:A	()Ljava/util/Map;
    //   702: putfield 303	com/tencent/bugly/crashreport/crash/CrashDetailBean:R	Ljava/util/Map;
    //   705: aload_0
    //   706: getfield 21	com/tencent/bugly/proguard/y:b	Lcom/tencent/bugly/crashreport/crash/b;
    //   709: aload 8
    //   711: invokevirtual 306	com/tencent/bugly/crashreport/crash/b:b	(Lcom/tencent/bugly/crashreport/crash/CrashDetailBean;)V
    //   714: aload 8
    //   716: ifnonnull +25 -> 741
    //   719: ldc_w 308
    //   722: iconst_0
    //   723: anewarray 4	java/lang/Object
    //   726: invokestatic 39	com/tencent/bugly/proguard/w:e	(Ljava/lang/String;[Ljava/lang/Object;)Z
    //   729: pop
    //   730: ldc 100
    //   732: iconst_0
    //   733: anewarray 4	java/lang/Object
    //   736: invokestatic 39	com/tencent/bugly/proguard/w:e	(Ljava/lang/String;[Ljava/lang/Object;)Z
    //   739: pop
    //   740: return
    //   741: ldc 70
    //   743: invokestatic 76	com/tencent/bugly/proguard/a:n	()Ljava/lang/String;
    //   746: aload_0
    //   747: getfield 25	com/tencent/bugly/proguard/y:d	Lcom/tencent/bugly/crashreport/common/info/a;
    //   750: getfield 81	com/tencent/bugly/crashreport/common/info/a:d	Ljava/lang/String;
    //   753: aload_1
    //   754: new 83	java/lang/StringBuilder
    //   757: dup
    //   758: invokespecial 84	java/lang/StringBuilder:<init>	()V
    //   761: aload_3
    //   762: invokevirtual 88	java/lang/StringBuilder:append	(Ljava/lang/String;)Ljava/lang/StringBuilder;
    //   765: ldc 90
    //   767: invokevirtual 88	java/lang/StringBuilder:append	(Ljava/lang/String;)Ljava/lang/StringBuilder;
    //   770: aload 4
    //   772: invokevirtual 88	java/lang/StringBuilder:append	(Ljava/lang/String;)Ljava/lang/StringBuilder;
    //   775: ldc 90
    //   777: invokevirtual 88	java/lang/StringBuilder:append	(Ljava/lang/String;)Ljava/lang/StringBuilder;
    //   780: aload 5
    //   782: invokevirtual 88	java/lang/StringBuilder:append	(Ljava/lang/String;)Ljava/lang/StringBuilder;
    //   785: invokevirtual 93	java/lang/StringBuilder:toString	()Ljava/lang/String;
    //   788: aload 8
    //   790: invokestatic 98	com/tencent/bugly/crashreport/crash/b:a	(Ljava/lang/String;Ljava/lang/String;Ljava/lang/String;Ljava/lang/Thread;Ljava/lang/String;Lcom/tencent/bugly/crashreport/crash/CrashDetailBean;)V
    //   793: aload_0
    //   794: getfield 21	com/tencent/bugly/proguard/y:b	Lcom/tencent/bugly/crashreport/crash/b;
    //   797: aload 8
    //   799: invokevirtual 311	com/tencent/bugly/crashreport/crash/b:a	(Lcom/tencent/bugly/crashreport/crash/CrashDetailBean;)Z
    //   802: ifne +16 -> 818
    //   805: aload_0
    //   806: getfield 21	com/tencent/bugly/proguard/y:b	Lcom/tencent/bugly/crashreport/crash/b;
    //   809: aload 8
    //   811: ldc2_w 312
    //   814: iconst_0
    //   815: invokevirtual 316	com/tencent/bugly/crashreport/crash/b:a	(Lcom/tencent/bugly/crashreport/crash/CrashDetailBean;JZ)V
    //   818: ldc 100
    //   820: iconst_0
    //   821: anewarray 4	java/lang/Object
    //   824: invokestatic 39	com/tencent/bugly/proguard/w:e	(Ljava/lang/String;[Ljava/lang/Object;)Z
    //   827: pop
    //   828: return
    //   829: astore_1
    //   830: ldc 100
    //   832: iconst_0
    //   833: anewarray 4	java/lang/Object
    //   836: invokestatic 39	com/tencent/bugly/proguard/w:e	(Ljava/lang/String;[Ljava/lang/Object;)Z
    //   839: pop
    //   840: aload_1
    //   841: athrow
    // Local variable table:
    //   start	length	slot	name	signature
    //   0	842	0	this	y
    //   0	842	1	paramThread	Thread
    //   0	842	2	paramInt	int
    //   0	842	3	paramString1	String
    //   0	842	4	paramString2	String
    //   0	842	5	paramString3	String
    //   108	3	6	localStrategyBean	com.tencent.bugly.crashreport.common.strategy.StrategyBean
    //   200	34	6	localInterruptedException	InterruptedException
    //   455	44	6	localObject	Object
    //   451	30	7	str	String
    //   269	541	8	localCrashDetailBean	com.tencent.bugly.crashreport.crash.CrashDetailBean
    //   469	22	9	arrayOfString	String[]
    //   39	33	10	i	int
    //   67	12	11	j	int
    //   48	3	12	bool	boolean
    // Exception table:
    //   from	to	target	type
    //   55	61	200	java/lang/InterruptedException
    //   10	38	210	java/lang/Throwable
    //   41	50	210	java/lang/Throwable
    //   55	61	210	java/lang/Throwable
    //   81	101	210	java/lang/Throwable
    //   101	189	210	java/lang/Throwable
    //   202	207	210	java/lang/Throwable
    //   233	251	210	java/lang/Throwable
    //   262	449	210	java/lang/Throwable
    //   462	471	210	java/lang/Throwable
    //   484	490	210	java/lang/Throwable
    //   496	714	210	java/lang/Throwable
    //   719	730	210	java/lang/Throwable
    //   741	818	210	java/lang/Throwable
    //   10	38	829	finally
    //   41	50	829	finally
    //   55	61	829	finally
    //   81	101	829	finally
    //   101	189	829	finally
    //   202	207	829	finally
    //   211	222	829	finally
    //   233	251	829	finally
    //   262	449	829	finally
    //   462	471	829	finally
    //   484	490	829	finally
    //   496	714	829	finally
    //   719	730	829	finally
    //   741	818	829	finally
  }
}


/* Location:              E:\apk\xiaoenai2\classes2-dex2jar.jar!\com\tencent\bugly\proguard\y.class
 * Java compiler version: 6 (50.0)
 * JD-Core Version:       0.7.1
 */