package com.alipay.apmobilesecuritysdk.a;

import android.content.Context;
import com.alipay.apmobilesecuritysdk.e.b;
import com.alipay.security.mobile.module.a.c;
import com.alipay.security.mobile.module.http.IUpload;
import com.alipay.security.mobile.module.http.UploadFactory;
import com.alipay.tscenter.biz.rpc.vkeydfp.request.DeviceDataReportRequest;
import java.util.HashMap;
import java.util.Map;

public class a
{
  private static final String b = a.class.getName();
  private static boolean c = false;
  private final Context a;
  
  public a(Context paramContext)
  {
    this.a = paramContext;
  }
  
  public static String a(Context paramContext)
  {
    Object localObject = "";
    try
    {
      String str = i.b();
      localObject = str;
      if (!com.alipay.security.mobile.module.a.a.a(str)) {
        return str;
      }
      localObject = str;
      e locale = d.a(paramContext);
      paramContext = str;
      if (locale != null)
      {
        localObject = str;
        paramContext = str;
        if (!com.alipay.security.mobile.module.a.a.a(locale.c()))
        {
          localObject = str;
          paramContext = locale.c();
          return paramContext;
        }
      }
    }
    catch (Throwable paramContext)
    {
      paramContext = (Context)localObject;
    }
    return paramContext;
  }
  
  private static void a(boolean paramBoolean)
  {
    try
    {
      c = paramBoolean;
      return;
    }
    finally
    {
      localObject = finally;
      throw ((Throwable)localObject);
    }
  }
  
  private static boolean a()
  {
    try
    {
      boolean bool = c;
      return bool;
    }
    finally
    {
      localObject = finally;
      throw ((Throwable)localObject);
    }
  }
  
  private g b(Map<String, String> paramMap)
  {
    for (;;)
    {
      try
      {
        Context localContext = this.a;
        DeviceDataReportRequest localDeviceDataReportRequest = new DeviceDataReportRequest();
        String str2 = "";
        String str1 = "";
        String str4 = com.alipay.security.mobile.module.a.a.a(paramMap, "umid", "");
        localObject2 = d.b(localContext);
        if (localObject2 != null)
        {
          str2 = ((e)localObject2).c();
          localObject1 = ((e)localObject2).a();
          localObject2 = ((e)localObject2).d();
          Object localObject3 = d.a();
          if (localObject3 != null) {
            str1 = ((e)localObject3).a();
          }
          String str3 = str1;
          localObject3 = localObject1;
          if (com.alipay.security.mobile.module.a.a.a((String)localObject1))
          {
            str3 = str1;
            localObject3 = localObject1;
            if (com.alipay.security.mobile.module.a.a.a(str1))
            {
              localObject3 = com.alipay.apmobilesecuritysdk.a.a.a.b(localContext);
              str3 = com.alipay.apmobilesecuritysdk.a.a.a.a();
            }
          }
          localDeviceDataReportRequest.os = "android";
          localDeviceDataReportRequest.priApdid = ((String)localObject3);
          localDeviceDataReportRequest.pubApdid = str3;
          localDeviceDataReportRequest.token = str2;
          localDeviceDataReportRequest.umidToken = str4;
          localDeviceDataReportRequest.lastTime = ((String)localObject2);
          localDeviceDataReportRequest.version = "3";
          localObject1 = new HashMap();
          ((Map)localObject1).putAll(com.alipay.apmobilesecuritysdk.d.d.a(localContext, paramMap));
          localDeviceDataReportRequest.dataMap = ((Map)localObject1);
          if (localDeviceDataReportRequest.dataMap != null)
          {
            paramMap = localDeviceDataReportRequest.dataMap;
            com.alipay.security.mobile.module.b.a.a();
            paramMap.put("AL3", com.alipay.security.mobile.module.b.a.l(localContext));
            localObject1 = localDeviceDataReportRequest.dataMap;
            paramMap = h.d(localContext);
            str1 = h.c(localContext);
            if (com.alipay.security.mobile.module.a.a.a(paramMap)) {
              break label330;
            }
            if (com.alipay.security.mobile.module.a.a.a(str1))
            {
              break label330;
              ((Map)localObject1).put("AA5", paramMap);
            }
          }
          else
          {
            return new g(UploadFactory.create(this.a, com.alipay.apmobilesecuritysdk.b.a.b).updateStaticData(localDeviceDataReportRequest));
          }
          com.alipay.security.mobile.module.b.a.a();
          paramMap = com.alipay.apmobilesecuritysdk.e.a.a(com.alipay.security.mobile.module.b.a.m(localContext), str1, paramMap);
          continue;
        }
        Object localObject1 = "";
      }
      catch (Throwable paramMap)
      {
        c.a(paramMap);
        return null;
      }
      Object localObject2 = "";
      continue;
      label330:
      paramMap = "";
    }
  }
  
  public static String b(Context paramContext)
  {
    Object localObject1 = "";
    Object localObject2;
    try
    {
      localObject2 = i.a();
      localObject1 = localObject2;
      if (!com.alipay.security.mobile.module.a.a.a((String)localObject2)) {
        return (String)localObject2;
      }
      localObject1 = localObject2;
      Object localObject3 = d.a(paramContext);
      if (localObject3 != null)
      {
        localObject1 = localObject2;
        if (!com.alipay.security.mobile.module.a.a.a(((e)localObject3).a()))
        {
          localObject1 = localObject2;
          return ((e)localObject3).a();
        }
      }
      localObject1 = localObject2;
      localObject3 = com.alipay.apmobilesecuritysdk.a.a.a.a(paramContext);
      localObject1 = localObject3;
      localObject2 = localObject3;
      if (com.alipay.security.mobile.module.a.a.a((String)localObject3))
      {
        localObject1 = localObject3;
        paramContext = b.a(paramContext);
        localObject1 = paramContext;
        boolean bool = com.alipay.security.mobile.module.a.a.a(paramContext);
        localObject2 = paramContext;
        if (!bool) {
          return paramContext;
        }
      }
    }
    catch (Throwable paramContext)
    {
      localObject2 = localObject1;
    }
    return (String)localObject2;
  }
  
  /* Error */
  public final String a(Map<String, String> paramMap)
  {
    // Byte code:
    //   0: aload_1
    //   1: ifnonnull +6 -> 7
    //   4: ldc 35
    //   6: areturn
    //   7: new 210	java/lang/StringBuilder
    //   10: dup
    //   11: invokespecial 211	java/lang/StringBuilder:<init>	()V
    //   14: aload_0
    //   15: getfield 29	com/alipay/apmobilesecuritysdk/a/a:a	Landroid/content/Context;
    //   18: invokevirtual 217	android/content/Context:getFilesDir	()Ljava/io/File;
    //   21: invokevirtual 222	java/io/File:getAbsolutePath	()Ljava/lang/String;
    //   24: invokevirtual 226	java/lang/StringBuilder:append	(Ljava/lang/String;)Ljava/lang/StringBuilder;
    //   27: ldc -28
    //   29: invokevirtual 226	java/lang/StringBuilder:append	(Ljava/lang/String;)Ljava/lang/StringBuilder;
    //   32: invokevirtual 231	java/lang/StringBuilder:toString	()Ljava/lang/String;
    //   35: astore_3
    //   36: getstatic 236	android/os/Build:MODEL	Ljava/lang/String;
    //   39: astore 4
    //   41: aload_0
    //   42: getfield 29	com/alipay/apmobilesecuritysdk/a/a:a	Landroid/content/Context;
    //   45: invokevirtual 240	android/content/Context:getApplicationContext	()Landroid/content/Context;
    //   48: invokevirtual 244	android/content/Context:getApplicationInfo	()Landroid/content/pm/ApplicationInfo;
    //   51: getfield 249	android/content/pm/ApplicationInfo:packageName	Ljava/lang/String;
    //   54: astore 5
    //   56: aload_1
    //   57: ldc -5
    //   59: ldc 35
    //   61: invokestatic 107	com/alipay/security/mobile/module/a/a:a	(Ljava/util/Map;Ljava/lang/String;Ljava/lang/String;)Ljava/lang/String;
    //   64: astore 6
    //   66: aload_1
    //   67: ldc -3
    //   69: ldc 35
    //   71: invokestatic 107	com/alipay/security/mobile/module/a/a:a	(Ljava/util/Map;Ljava/lang/String;Ljava/lang/String;)Ljava/lang/String;
    //   74: astore 7
    //   76: ldc 35
    //   78: astore_2
    //   79: aload_0
    //   80: getfield 29	com/alipay/apmobilesecuritysdk/a/a:a	Landroid/content/Context;
    //   83: invokestatic 49	com/alipay/apmobilesecuritysdk/a/d:a	(Landroid/content/Context;)Lcom/alipay/apmobilesecuritysdk/a/e;
    //   86: astore 8
    //   88: aload 8
    //   90: ifnull +9 -> 99
    //   93: aload 8
    //   95: invokevirtual 111	com/alipay/apmobilesecuritysdk/a/e:a	()Ljava/lang/String;
    //   98: astore_2
    //   99: new 255	com/alipay/apmobilesecuritysdk/c/a
    //   102: dup
    //   103: aload 4
    //   105: aload 5
    //   107: ldc_w 257
    //   110: ldc_w 259
    //   113: aload 6
    //   115: aload 7
    //   117: aload_2
    //   118: invokespecial 262	com/alipay/apmobilesecuritysdk/c/a:<init>	(Ljava/lang/String;Ljava/lang/String;Ljava/lang/String;Ljava/lang/String;Ljava/lang/String;Ljava/lang/String;Ljava/lang/String;)V
    //   121: astore_2
    //   122: invokestatic 268	java/util/Calendar:getInstance	()Ljava/util/Calendar;
    //   125: invokevirtual 272	java/util/Calendar:getTime	()Ljava/util/Date;
    //   128: astore 4
    //   130: new 274	java/text/SimpleDateFormat
    //   133: dup
    //   134: ldc_w 276
    //   137: invokespecial 279	java/text/SimpleDateFormat:<init>	(Ljava/lang/String;)V
    //   140: aload 4
    //   142: invokevirtual 283	java/text/SimpleDateFormat:format	(Ljava/util/Date;)Ljava/lang/String;
    //   145: astore 4
    //   147: aload_3
    //   148: new 210	java/lang/StringBuilder
    //   151: dup
    //   152: invokespecial 211	java/lang/StringBuilder:<init>	()V
    //   155: aload 4
    //   157: invokevirtual 226	java/lang/StringBuilder:append	(Ljava/lang/String;)Ljava/lang/StringBuilder;
    //   160: ldc_w 285
    //   163: invokevirtual 226	java/lang/StringBuilder:append	(Ljava/lang/String;)Ljava/lang/StringBuilder;
    //   166: invokevirtual 231	java/lang/StringBuilder:toString	()Ljava/lang/String;
    //   169: aload_2
    //   170: invokevirtual 286	com/alipay/apmobilesecuritysdk/c/a:toString	()Ljava/lang/String;
    //   173: invokestatic 289	com/alipay/security/mobile/module/a/c:a	(Ljava/lang/String;Ljava/lang/String;Ljava/lang/String;)V
    //   176: new 291	java/lang/Thread
    //   179: dup
    //   180: new 293	com/alipay/apmobilesecuritysdk/a/b
    //   183: dup
    //   184: aload_0
    //   185: invokespecial 296	com/alipay/apmobilesecuritysdk/a/b:<init>	(Lcom/alipay/apmobilesecuritysdk/a/a;)V
    //   188: invokespecial 299	java/lang/Thread:<init>	(Ljava/lang/Runnable;)V
    //   191: invokevirtual 302	java/lang/Thread:start	()V
    //   194: aload_1
    //   195: ldc_w 304
    //   198: ldc 35
    //   200: invokestatic 107	com/alipay/security/mobile/module/a/a:a	(Ljava/util/Map;Ljava/lang/String;Ljava/lang/String;)Ljava/lang/String;
    //   203: astore 5
    //   205: invokestatic 306	com/alipay/apmobilesecuritysdk/d/d:a	()V
    //   208: aload_0
    //   209: getfield 29	com/alipay/apmobilesecuritysdk/a/a:a	Landroid/content/Context;
    //   212: aload_1
    //   213: invokestatic 309	com/alipay/apmobilesecuritysdk/d/d:b	(Landroid/content/Context;Ljava/util/Map;)Ljava/lang/String;
    //   216: astore 4
    //   218: aload_0
    //   219: getfield 29	com/alipay/apmobilesecuritysdk/a/a:a	Landroid/content/Context;
    //   222: invokestatic 49	com/alipay/apmobilesecuritysdk/a/d:a	(Landroid/content/Context;)Lcom/alipay/apmobilesecuritysdk/a/e;
    //   225: astore_2
    //   226: aload_2
    //   227: ifnull +92 -> 319
    //   230: aload 4
    //   232: aload_2
    //   233: invokevirtual 310	com/alipay/apmobilesecuritysdk/a/e:b	()Ljava/lang/String;
    //   236: invokestatic 313	com/alipay/security/mobile/module/a/a:a	(Ljava/lang/String;Ljava/lang/String;)Z
    //   239: ifne +74 -> 313
    //   242: iconst_1
    //   243: istore 9
    //   245: aload_0
    //   246: getfield 29	com/alipay/apmobilesecuritysdk/a/a:a	Landroid/content/Context;
    //   249: invokestatic 316	com/alipay/apmobilesecuritysdk/a/i:a	(Landroid/content/Context;)Z
    //   252: istore 12
    //   254: iload 9
    //   256: ifne +69 -> 325
    //   259: iload 12
    //   261: ifeq +64 -> 325
    //   264: aload_2
    //   265: invokevirtual 53	com/alipay/apmobilesecuritysdk/a/e:c	()Ljava/lang/String;
    //   268: invokestatic 44	com/alipay/security/mobile/module/a/a:a	(Ljava/lang/String;)Z
    //   271: ifne +54 -> 325
    //   274: aload_2
    //   275: invokevirtual 53	com/alipay/apmobilesecuritysdk/a/e:c	()Ljava/lang/String;
    //   278: astore_1
    //   279: new 318	com/alipay/apmobilesecuritysdk/c/b
    //   282: dup
    //   283: aload_3
    //   284: aload_0
    //   285: getfield 29	com/alipay/apmobilesecuritysdk/a/a:a	Landroid/content/Context;
    //   288: getstatic 61	com/alipay/apmobilesecuritysdk/b/a:b	Lcom/alipay/security/mobile/module/http/UploadFactory$Mode;
    //   291: invokestatic 67	com/alipay/security/mobile/module/http/UploadFactory:create	(Landroid/content/Context;Lcom/alipay/security/mobile/module/http/UploadFactory$Mode;)Lcom/alipay/security/mobile/module/http/IUpload;
    //   294: invokespecial 321	com/alipay/apmobilesecuritysdk/c/b:<init>	(Ljava/lang/String;Lcom/alipay/security/mobile/module/http/IUpload;)V
    //   297: aload_0
    //   298: getfield 29	com/alipay/apmobilesecuritysdk/a/a:a	Landroid/content/Context;
    //   301: invokevirtual 323	com/alipay/apmobilesecuritysdk/c/b:a	(Landroid/content/Context;)V
    //   304: aload_1
    //   305: areturn
    //   306: astore_2
    //   307: aload_2
    //   308: invokestatic 98	com/alipay/security/mobile/module/a/c:a	(Ljava/lang/Throwable;)V
    //   311: aload_1
    //   312: areturn
    //   313: iconst_0
    //   314: istore 9
    //   316: goto -71 -> 245
    //   319: iconst_1
    //   320: istore 9
    //   322: goto -77 -> 245
    //   325: aload_0
    //   326: aload_1
    //   327: invokespecial 325	com/alipay/apmobilesecuritysdk/a/a:b	(Ljava/util/Map;)Lcom/alipay/apmobilesecuritysdk/a/g;
    //   330: astore 4
    //   332: aload 4
    //   334: ifnull +288 -> 622
    //   337: aload 4
    //   339: invokevirtual 326	com/alipay/apmobilesecuritysdk/a/g:a	()Z
    //   342: ifeq +280 -> 622
    //   345: getstatic 20	com/alipay/apmobilesecuritysdk/a/a:b	Ljava/lang/String;
    //   348: astore_2
    //   349: aload_0
    //   350: getfield 29	com/alipay/apmobilesecuritysdk/a/a:a	Landroid/content/Context;
    //   353: astore_2
    //   354: aload 4
    //   356: invokevirtual 329	com/alipay/apmobilesecuritysdk/a/g:f	()Z
    //   359: istore 12
    //   361: aload_2
    //   362: ldc_w 331
    //   365: iconst_0
    //   366: invokevirtual 335	android/content/Context:getSharedPreferences	(Ljava/lang/String;I)Landroid/content/SharedPreferences;
    //   369: invokeinterface 341 1 0
    //   374: astore 6
    //   376: aload 6
    //   378: ifnull +38 -> 416
    //   381: iload 12
    //   383: ifeq +211 -> 594
    //   386: invokestatic 344	com/alipay/security/mobile/module/a/a/c:a	()Ljava/lang/String;
    //   389: ldc_w 346
    //   392: invokestatic 349	com/alipay/security/mobile/module/a/a/c:a	(Ljava/lang/String;Ljava/lang/String;)Ljava/lang/String;
    //   395: astore_2
    //   396: aload 6
    //   398: ldc_w 351
    //   401: aload_2
    //   402: invokeinterface 357 3 0
    //   407: pop
    //   408: aload 6
    //   410: invokeinterface 360 1 0
    //   415: pop
    //   416: aload_0
    //   417: getfield 29	com/alipay/apmobilesecuritysdk/a/a:a	Landroid/content/Context;
    //   420: invokestatic 179	com/alipay/apmobilesecuritysdk/a/h:d	(Landroid/content/Context;)Ljava/lang/String;
    //   423: astore_2
    //   424: aload 4
    //   426: invokevirtual 363	com/alipay/apmobilesecuritysdk/a/g:g	()Ljava/lang/String;
    //   429: invokestatic 44	com/alipay/security/mobile/module/a/a:a	(Ljava/lang/String;)Z
    //   432: ifne +51 -> 483
    //   435: aload_2
    //   436: aload 4
    //   438: invokevirtual 363	com/alipay/apmobilesecuritysdk/a/g:g	()Ljava/lang/String;
    //   441: invokestatic 313	com/alipay/security/mobile/module/a/a:a	(Ljava/lang/String;Ljava/lang/String;)Z
    //   444: ifne +39 -> 483
    //   447: aload 4
    //   449: invokevirtual 364	com/alipay/apmobilesecuritysdk/a/g:c	()Ljava/lang/String;
    //   452: astore_2
    //   453: invokestatic 365	com/alipay/apmobilesecuritysdk/a/a:a	()Z
    //   456: ifne +27 -> 483
    //   459: iconst_1
    //   460: invokestatic 84	com/alipay/apmobilesecuritysdk/a/a:a	(Z)V
    //   463: new 367	com/alipay/apmobilesecuritysdk/a/c
    //   466: dup
    //   467: aload_0
    //   468: aload 5
    //   470: aload_2
    //   471: ldc 35
    //   473: invokespecial 369	com/alipay/apmobilesecuritysdk/a/c:<init>	(Lcom/alipay/apmobilesecuritysdk/a/a;Ljava/lang/String;Ljava/lang/String;Ljava/lang/String;)V
    //   476: invokevirtual 302	java/lang/Thread:start	()V
    //   479: iconst_0
    //   480: invokestatic 84	com/alipay/apmobilesecuritysdk/a/a:a	(Z)V
    //   483: aload_0
    //   484: getfield 29	com/alipay/apmobilesecuritysdk/a/a:a	Landroid/content/Context;
    //   487: aload_1
    //   488: invokestatic 309	com/alipay/apmobilesecuritysdk/d/d:b	(Landroid/content/Context;Ljava/util/Map;)Ljava/lang/String;
    //   491: astore_1
    //   492: aload 4
    //   494: ifnull +91 -> 585
    //   497: new 51	com/alipay/apmobilesecuritysdk/a/e
    //   500: dup
    //   501: aload 4
    //   503: aload_1
    //   504: invokespecial 372	com/alipay/apmobilesecuritysdk/a/e:<init>	(Lcom/alipay/apmobilesecuritysdk/a/g;Ljava/lang/String;)V
    //   507: astore_1
    //   508: aload_0
    //   509: getfield 29	com/alipay/apmobilesecuritysdk/a/a:a	Landroid/content/Context;
    //   512: aload_1
    //   513: invokestatic 375	com/alipay/apmobilesecuritysdk/a/d:a	(Landroid/content/Context;Lcom/alipay/apmobilesecuritysdk/a/e;)V
    //   516: aload_1
    //   517: invokestatic 378	com/alipay/apmobilesecuritysdk/a/i:a	(Lcom/alipay/apmobilesecuritysdk/a/e;)V
    //   520: aload_0
    //   521: getfield 29	com/alipay/apmobilesecuritysdk/a/a:a	Landroid/content/Context;
    //   524: astore_2
    //   525: aload_1
    //   526: invokestatic 379	com/alipay/apmobilesecuritysdk/a/a/a:a	(Lcom/alipay/apmobilesecuritysdk/a/e;)V
    //   529: aload_0
    //   530: getfield 29	com/alipay/apmobilesecuritysdk/a/a:a	Landroid/content/Context;
    //   533: astore_1
    //   534: invokestatic 385	java/lang/System:currentTimeMillis	()J
    //   537: lstore 10
    //   539: aload_1
    //   540: ldc_w 331
    //   543: iconst_0
    //   544: invokevirtual 335	android/content/Context:getSharedPreferences	(Ljava/lang/String;I)Landroid/content/SharedPreferences;
    //   547: invokeinterface 341 1 0
    //   552: astore_1
    //   553: aload_1
    //   554: ifnull +31 -> 585
    //   557: aload_1
    //   558: ldc_w 387
    //   561: invokestatic 344	com/alipay/security/mobile/module/a/a/c:a	()Ljava/lang/String;
    //   564: lload 10
    //   566: invokestatic 393	java/lang/String:valueOf	(J)Ljava/lang/String;
    //   569: invokestatic 349	com/alipay/security/mobile/module/a/a/c:a	(Ljava/lang/String;Ljava/lang/String;)Ljava/lang/String;
    //   572: invokeinterface 357 3 0
    //   577: pop
    //   578: aload_1
    //   579: invokeinterface 360 1 0
    //   584: pop
    //   585: aload 4
    //   587: invokevirtual 364	com/alipay/apmobilesecuritysdk/a/g:c	()Ljava/lang/String;
    //   590: astore_1
    //   591: goto -312 -> 279
    //   594: invokestatic 344	com/alipay/security/mobile/module/a/a/c:a	()Ljava/lang/String;
    //   597: ldc_w 395
    //   600: invokestatic 349	com/alipay/security/mobile/module/a/a/c:a	(Ljava/lang/String;Ljava/lang/String;)Ljava/lang/String;
    //   603: astore_2
    //   604: goto -208 -> 396
    //   607: astore_2
    //   608: iconst_0
    //   609: invokestatic 84	com/alipay/apmobilesecuritysdk/a/a:a	(Z)V
    //   612: goto -129 -> 483
    //   615: astore_1
    //   616: iconst_0
    //   617: invokestatic 84	com/alipay/apmobilesecuritysdk/a/a:a	(Z)V
    //   620: aload_1
    //   621: athrow
    //   622: aload 4
    //   624: ifnull +49 -> 673
    //   627: new 210	java/lang/StringBuilder
    //   630: dup
    //   631: ldc_w 397
    //   634: invokespecial 398	java/lang/StringBuilder:<init>	(Ljava/lang/String;)V
    //   637: aload 4
    //   639: invokevirtual 401	com/alipay/apmobilesecuritysdk/a/g:e	()Ljava/lang/String;
    //   642: invokevirtual 226	java/lang/StringBuilder:append	(Ljava/lang/String;)Ljava/lang/StringBuilder;
    //   645: invokevirtual 231	java/lang/StringBuilder:toString	()Ljava/lang/String;
    //   648: invokestatic 403	com/alipay/security/mobile/module/a/c:a	(Ljava/lang/String;)V
    //   651: aload_2
    //   652: ifnull +30 -> 682
    //   655: aload_2
    //   656: invokevirtual 53	com/alipay/apmobilesecuritysdk/a/e:c	()Ljava/lang/String;
    //   659: invokestatic 44	com/alipay/security/mobile/module/a/a:a	(Ljava/lang/String;)Z
    //   662: ifne +20 -> 682
    //   665: aload_2
    //   666: invokevirtual 53	com/alipay/apmobilesecuritysdk/a/e:c	()Ljava/lang/String;
    //   669: astore_1
    //   670: goto -391 -> 279
    //   673: ldc_w 405
    //   676: invokestatic 403	com/alipay/security/mobile/module/a/c:a	(Ljava/lang/String;)V
    //   679: goto -28 -> 651
    //   682: ldc 35
    //   684: astore_1
    //   685: goto -406 -> 279
    //   688: astore_1
    //   689: goto -104 -> 585
    //   692: astore_2
    //   693: goto -277 -> 416
    //   696: astore_2
    //   697: ldc 35
    //   699: astore_1
    //   700: goto -393 -> 307
    // Local variable table:
    //   start	length	slot	name	signature
    //   0	703	0	this	a
    //   0	703	1	paramMap	Map<String, String>
    //   78	197	2	localObject1	Object
    //   306	2	2	localThrowable1	Throwable
    //   348	256	2	localObject2	Object
    //   607	59	2	localThrowable2	Throwable
    //   692	1	2	localThrowable3	Throwable
    //   696	1	2	localThrowable4	Throwable
    //   35	249	3	str1	String
    //   39	599	4	localObject3	Object
    //   54	415	5	str2	String
    //   64	345	6	localObject4	Object
    //   74	42	7	str3	String
    //   86	8	8	locale	e
    //   243	78	9	i	int
    //   537	28	10	l	long
    //   252	130	12	bool	boolean
    // Exception table:
    //   from	to	target	type
    //   279	304	306	java/lang/Throwable
    //   463	479	607	java/lang/Throwable
    //   463	479	615	finally
    //   539	553	688	java/lang/Throwable
    //   557	585	688	java/lang/Throwable
    //   361	376	692	java/lang/Throwable
    //   386	396	692	java/lang/Throwable
    //   396	416	692	java/lang/Throwable
    //   594	604	692	java/lang/Throwable
    //   7	76	696	java/lang/Throwable
    //   79	88	696	java/lang/Throwable
    //   93	99	696	java/lang/Throwable
    //   99	226	696	java/lang/Throwable
    //   230	242	696	java/lang/Throwable
    //   245	254	696	java/lang/Throwable
    //   264	279	696	java/lang/Throwable
    //   325	332	696	java/lang/Throwable
    //   337	361	696	java/lang/Throwable
    //   416	463	696	java/lang/Throwable
    //   479	483	696	java/lang/Throwable
    //   483	492	696	java/lang/Throwable
    //   497	539	696	java/lang/Throwable
    //   585	591	696	java/lang/Throwable
    //   608	612	696	java/lang/Throwable
    //   616	622	696	java/lang/Throwable
    //   627	651	696	java/lang/Throwable
    //   655	670	696	java/lang/Throwable
    //   673	679	696	java/lang/Throwable
  }
}


/* Location:              E:\apk\xiaoenai2\classes-dex2jar.jar!\com\alipay\apmobilesecuritysdk\a\a.class
 * Java compiler version: 6 (50.0)
 * JD-Core Version:       0.7.1
 */