package com.adhoc;

import java.io.IOException;

class v
  implements an
{
  v(s params) {}
  
  public void a(bj parambj, IOException paramIOException)
  {
    try
    {
      fl.b(parambj.c() + " error");
      return;
    }
    catch (Throwable parambj)
    {
      fl.a(parambj);
    }
  }
  
  /* Error */
  public void a(bn parambn)
  {
    // Byte code:
    //   0: aload_1
    //   1: ifnull +109 -> 110
    //   4: aload_1
    //   5: invokevirtual 55	com/adhoc/bn:d	()Z
    //   8: ifne +25 -> 33
    //   11: aload_1
    //   12: invokevirtual 58	com/adhoc/bn:e	()Ljava/lang/String;
    //   15: invokevirtual 61	java/lang/String:toString	()Ljava/lang/String;
    //   18: invokestatic 43	com/adhoc/fl:b	(Ljava/lang/String;)V
    //   21: aload_1
    //   22: ifnull +10 -> 32
    //   25: aload_1
    //   26: invokevirtual 65	com/adhoc/bn:h	()Lcom/adhoc/bp;
    //   29: invokevirtual 70	com/adhoc/bp:close	()V
    //   32: return
    //   33: aload_1
    //   34: invokevirtual 65	com/adhoc/bn:h	()Lcom/adhoc/bp;
    //   37: invokevirtual 71	com/adhoc/bp:e	()Ljava/lang/String;
    //   40: astore_3
    //   41: aload_3
    //   42: ldc 73
    //   44: invokevirtual 77	java/lang/String:equals	(Ljava/lang/Object;)Z
    //   47: ifne +75 -> 122
    //   50: new 79	org/json/JSONObject
    //   53: dup
    //   54: aload_3
    //   55: invokespecial 81	org/json/JSONObject:<init>	(Ljava/lang/String;)V
    //   58: astore_2
    //   59: new 21	java/lang/StringBuilder
    //   62: dup
    //   63: invokespecial 22	java/lang/StringBuilder:<init>	()V
    //   66: ldc 83
    //   68: invokevirtual 32	java/lang/StringBuilder:append	(Ljava/lang/String;)Ljava/lang/StringBuilder;
    //   71: aload_3
    //   72: invokevirtual 32	java/lang/StringBuilder:append	(Ljava/lang/String;)Ljava/lang/StringBuilder;
    //   75: invokevirtual 37	java/lang/StringBuilder:toString	()Ljava/lang/String;
    //   78: invokestatic 85	com/adhoc/fl:a	(Ljava/lang/String;)V
    //   81: aload_0
    //   82: getfield 12	com/adhoc/v:a	Lcom/adhoc/s;
    //   85: aload_2
    //   86: invokestatic 90	com/adhoc/s:a	(Lcom/adhoc/s;Lorg/json/JSONObject;)Lorg/json/JSONObject;
    //   89: astore_2
    //   90: invokestatic 95	com/adhoc/q:a	()Lcom/adhoc/q;
    //   93: aload_2
    //   94: invokevirtual 98	com/adhoc/q:a	(Lorg/json/JSONObject;)V
    //   97: aload_0
    //   98: getfield 12	com/adhoc/v:a	Lcom/adhoc/s;
    //   101: invokestatic 101	com/adhoc/s:a	(Lcom/adhoc/s;)Landroid/content/Context;
    //   104: ldc 103
    //   106: iconst_1
    //   107: invokestatic 109	com/adhoc/adhocsdk/AdhocTracker:incrementStat	(Landroid/content/Context;Ljava/lang/String;I)V
    //   110: aload_1
    //   111: ifnull -79 -> 32
    //   114: aload_1
    //   115: invokevirtual 65	com/adhoc/bn:h	()Lcom/adhoc/bp;
    //   118: invokevirtual 70	com/adhoc/bp:close	()V
    //   121: return
    //   122: new 79	org/json/JSONObject
    //   125: dup
    //   126: invokespecial 110	org/json/JSONObject:<init>	()V
    //   129: astore_2
    //   130: new 21	java/lang/StringBuilder
    //   133: dup
    //   134: invokespecial 22	java/lang/StringBuilder:<init>	()V
    //   137: ldc 112
    //   139: invokevirtual 32	java/lang/StringBuilder:append	(Ljava/lang/String;)Ljava/lang/StringBuilder;
    //   142: aload_3
    //   143: invokevirtual 32	java/lang/StringBuilder:append	(Ljava/lang/String;)Ljava/lang/StringBuilder;
    //   146: invokevirtual 37	java/lang/StringBuilder:toString	()Ljava/lang/String;
    //   149: invokestatic 85	com/adhoc/fl:a	(Ljava/lang/String;)V
    //   152: goto -93 -> 59
    //   155: astore_2
    //   156: ldc 114
    //   158: invokestatic 43	com/adhoc/fl:b	(Ljava/lang/String;)V
    //   161: goto -51 -> 110
    //   164: astore_2
    //   165: aload_2
    //   166: invokestatic 46	com/adhoc/fl:a	(Ljava/lang/Throwable;)V
    //   169: aload_1
    //   170: ifnull -138 -> 32
    //   173: aload_1
    //   174: invokevirtual 65	com/adhoc/bn:h	()Lcom/adhoc/bp;
    //   177: invokevirtual 70	com/adhoc/bp:close	()V
    //   180: return
    //   181: astore_2
    //   182: aload_2
    //   183: invokestatic 46	com/adhoc/fl:a	(Ljava/lang/Throwable;)V
    //   186: goto -76 -> 110
    //   189: astore_2
    //   190: aload_1
    //   191: ifnull +10 -> 201
    //   194: aload_1
    //   195: invokevirtual 65	com/adhoc/bn:h	()Lcom/adhoc/bp;
    //   198: invokevirtual 70	com/adhoc/bp:close	()V
    //   201: aload_2
    //   202: athrow
    // Local variable table:
    //   start	length	slot	name	signature
    //   0	203	0	this	v
    //   0	203	1	parambn	bn
    //   58	72	2	localJSONObject	org.json.JSONObject
    //   155	1	2	localJSONException	org.json.JSONException
    //   164	2	2	localThrowable1	Throwable
    //   181	2	2	localThrowable2	Throwable
    //   189	13	2	localObject	Object
    //   40	103	3	str	String
    // Exception table:
    //   from	to	target	type
    //   41	59	155	org/json/JSONException
    //   59	110	155	org/json/JSONException
    //   122	152	155	org/json/JSONException
    //   4	21	164	java/lang/Throwable
    //   33	41	164	java/lang/Throwable
    //   156	161	164	java/lang/Throwable
    //   182	186	164	java/lang/Throwable
    //   41	59	181	java/lang/Throwable
    //   59	110	181	java/lang/Throwable
    //   122	152	181	java/lang/Throwable
    //   4	21	189	finally
    //   33	41	189	finally
    //   41	59	189	finally
    //   59	110	189	finally
    //   122	152	189	finally
    //   156	161	189	finally
    //   165	169	189	finally
    //   182	186	189	finally
  }
}


/* Location:              E:\apk\xiaoenai2\classes-dex2jar.jar!\com\adhoc\v.class
 * Java compiler version: 6 (50.0)
 * JD-Core Version:       0.7.1
 */