package com.adhoc;

import android.content.Context;

class x
  implements Runnable
{
  x(w paramw, Context paramContext) {}
  
  /* Error */
  public void run()
  {
    // Byte code:
    //   0: invokestatic 30	com/adhoc/r:a	()Lcom/adhoc/r;
    //   3: aload_0
    //   4: getfield 16	com/adhoc/x:a	Landroid/content/Context;
    //   7: ldc 32
    //   9: invokevirtual 35	com/adhoc/r:b	(Landroid/content/Context;Ljava/lang/String;)Ljava/util/ArrayList;
    //   12: astore_1
    //   13: aload_1
    //   14: invokevirtual 41	java/util/ArrayList:size	()I
    //   17: ifle +15 -> 32
    //   20: invokestatic 30	com/adhoc/r:a	()Lcom/adhoc/r;
    //   23: aload_0
    //   24: getfield 16	com/adhoc/x:a	Landroid/content/Context;
    //   27: ldc 32
    //   29: invokevirtual 44	com/adhoc/r:a	(Landroid/content/Context;Ljava/lang/String;)V
    //   32: aload_1
    //   33: invokevirtual 48	java/util/ArrayList:iterator	()Ljava/util/Iterator;
    //   36: astore_1
    //   37: aload_1
    //   38: invokeinterface 54 1 0
    //   43: ifeq +71 -> 114
    //   46: aload_1
    //   47: invokeinterface 58 1 0
    //   52: checkcast 60	java/lang/String
    //   55: astore_2
    //   56: aload_0
    //   57: getfield 14	com/adhoc/x:b	Lcom/adhoc/w;
    //   60: iconst_1
    //   61: invokestatic 65	com/adhoc/w:a	(Lcom/adhoc/w;Z)Z
    //   64: pop
    //   65: aload_0
    //   66: getfield 14	com/adhoc/x:b	Lcom/adhoc/w;
    //   69: invokestatic 68	com/adhoc/w:a	(Lcom/adhoc/w;)J
    //   72: invokestatic 74	java/lang/Thread:sleep	(J)V
    //   75: aload_0
    //   76: getfield 14	com/adhoc/x:b	Lcom/adhoc/w;
    //   79: new 76	org/json/JSONObject
    //   82: dup
    //   83: aload_2
    //   84: invokespecial 79	org/json/JSONObject:<init>	(Ljava/lang/String;)V
    //   87: aload_0
    //   88: getfield 16	com/adhoc/x:a	Landroid/content/Context;
    //   91: invokestatic 82	com/adhoc/w:a	(Lcom/adhoc/w;Lorg/json/JSONObject;Landroid/content/Context;)V
    //   94: goto -57 -> 37
    //   97: astore_2
    //   98: ldc 84
    //   100: invokestatic 88	com/adhoc/fl:b	(Ljava/lang/String;)V
    //   103: goto -66 -> 37
    //   106: astore_3
    //   107: aload_3
    //   108: invokestatic 91	com/adhoc/fl:a	(Ljava/lang/Exception;)V
    //   111: goto -36 -> 75
    //   114: aload_0
    //   115: getfield 14	com/adhoc/x:b	Lcom/adhoc/w;
    //   118: iconst_0
    //   119: invokestatic 65	com/adhoc/w:a	(Lcom/adhoc/w;Z)Z
    //   122: pop
    //   123: return
    // Local variable table:
    //   start	length	slot	name	signature
    //   0	124	0	this	x
    //   12	35	1	localObject	Object
    //   55	29	2	str	String
    //   97	1	2	localThrowable	Throwable
    //   106	2	3	localInterruptedException	InterruptedException
    // Exception table:
    //   from	to	target	type
    //   56	65	97	java/lang/Throwable
    //   65	75	97	java/lang/Throwable
    //   75	94	97	java/lang/Throwable
    //   107	111	97	java/lang/Throwable
    //   65	75	106	java/lang/InterruptedException
  }
}


/* Location:              E:\apk\xiaoenai2\classes-dex2jar.jar!\com\adhoc\x.class
 * Java compiler version: 6 (50.0)
 * JD-Core Version:       0.7.1
 */