package b.a.a;

import b.ai;
import java.io.Closeable;
import java.io.IOException;
import java.io.InterruptedIOException;
import java.net.Socket;
import java.util.Collection;
import java.util.HashMap;
import java.util.LinkedHashSet;
import java.util.List;
import java.util.Map;
import java.util.Set;
import java.util.concurrent.ExecutorService;
import java.util.concurrent.LinkedBlockingQueue;
import java.util.concurrent.SynchronousQueue;
import java.util.concurrent.ThreadPoolExecutor;
import java.util.concurrent.TimeUnit;

public final class d
  implements Closeable
{
  private static final ExecutorService l;
  final ai a;
  final boolean b;
  long c = 0L;
  long d;
  ac e = new ac();
  final ac f = new ac();
  final ae g;
  final Socket h;
  final c i;
  final c j;
  private final b m;
  private final Map<Integer, p> n = new HashMap();
  private final String o;
  private int p;
  private int q;
  private boolean r;
  private long s = System.nanoTime();
  private final ExecutorService t;
  private Map<Integer, z> u;
  private final aa v;
  private int w;
  private boolean x = false;
  private final Set<Integer> y = new LinkedHashSet();
  
  static
  {
    if (!d.class.desiredAssertionStatus()) {}
    for (boolean bool = true;; bool = false)
    {
      k = bool;
      l = new ThreadPoolExecutor(0, Integer.MAX_VALUE, 60L, TimeUnit.SECONDS, new SynchronousQueue(), b.a.j.a("OkHttp FramedConnection", true));
      return;
    }
  }
  
  private d(a parama)
  {
    this.a = a.a(parama);
    this.v = a.b(parama);
    this.b = a.c(parama);
    this.m = a.d(parama);
    int i1;
    if (a.c(parama))
    {
      i1 = 1;
      this.q = i1;
      if ((a.c(parama)) && (this.a == ai.d)) {
        this.q += 2;
      }
      i1 = i2;
      if (a.c(parama)) {
        i1 = 1;
      }
      this.w = i1;
      if (a.c(parama)) {
        this.e.a(7, 0, 16777216);
      }
      this.o = a.e(parama);
      if (this.a != ai.d) {
        break label370;
      }
      this.g = new u();
      this.t = new ThreadPoolExecutor(0, 1, 60L, TimeUnit.SECONDS, new LinkedBlockingQueue(), b.a.j.a(String.format("OkHttp %s Push Observer", new Object[] { this.o }), true));
      this.f.a(7, 0, 65535);
      this.f.a(5, 0, 16384);
    }
    for (;;)
    {
      this.d = this.f.f(65536);
      this.h = a.f(parama);
      this.i = this.g.a(a.g(parama), this.b);
      this.j = new c(this.g.a(a.h(parama), this.b), null);
      new Thread(this.j).start();
      return;
      i1 = 2;
      break;
      label370:
      if (this.a != ai.c) {
        break label399;
      }
      this.g = new ad();
      this.t = null;
    }
    label399:
    throw new AssertionError(this.a);
  }
  
  private p a(int paramInt, List<r> paramList, boolean paramBoolean1, boolean paramBoolean2)
  {
    boolean bool2 = true;
    boolean bool1;
    if (!paramBoolean1)
    {
      bool1 = true;
      if (paramBoolean2) {
        break label64;
      }
    }
    label64:
    for (paramBoolean2 = bool2;; paramBoolean2 = false)
    {
      synchronized (this.i)
      {
        try
        {
          if (!this.r) {
            break label70;
          }
          throw new IOException("shutdown");
        }
        finally {}
      }
      bool1 = false;
      break;
    }
    label70:
    int i1 = this.q;
    this.q += 2;
    p localp = new p(i1, this, bool1, paramBoolean2, paramList);
    if (localp.b())
    {
      this.n.put(Integer.valueOf(i1), localp);
      a(false);
    }
    if (paramInt == 0) {
      this.i.a(bool1, paramBoolean2, i1, paramInt, paramList);
    }
    for (;;)
    {
      if (!paramBoolean1) {
        this.i.b();
      }
      return localp;
      if (this.b) {
        throw new IllegalArgumentException("client streams shouldn't have associated stream IDs");
      }
      this.i.a(paramInt, i1, paramList);
    }
  }
  
  private void a(int paramInt1, c.h paramh, int paramInt2, boolean paramBoolean)
  {
    c.e locale = new c.e();
    paramh.a(paramInt2);
    paramh.a(locale, paramInt2);
    if (locale.b() != paramInt2) {
      throw new IOException(locale.b() + " != " + paramInt2);
    }
    this.t.execute(new j(this, "OkHttp %s Push Data[%s]", new Object[] { this.o, Integer.valueOf(paramInt1) }, paramInt1, locale, paramInt2, paramBoolean));
  }
  
  private void a(int paramInt, List<r> paramList)
  {
    try
    {
      if (this.y.contains(Integer.valueOf(paramInt)))
      {
        a(paramInt, a.b);
        return;
      }
      this.y.add(Integer.valueOf(paramInt));
      this.t.execute(new h(this, "OkHttp %s Push Request[%s]", new Object[] { this.o, Integer.valueOf(paramInt) }, paramInt, paramList));
      return;
    }
    finally {}
  }
  
  private void a(int paramInt, List<r> paramList, boolean paramBoolean)
  {
    this.t.execute(new i(this, "OkHttp %s Push Headers[%s]", new Object[] { this.o, Integer.valueOf(paramInt) }, paramInt, paramList, paramBoolean));
  }
  
  /* Error */
  private void a(a parama1, a parama2)
  {
    // Byte code:
    //   0: getstatic 65	b/a/a/d:k	Z
    //   3: ifne +18 -> 21
    //   6: aload_0
    //   7: invokestatic 368	java/lang/Thread:holdsLock	(Ljava/lang/Object;)Z
    //   10: ifeq +11 -> 21
    //   13: new 228	java/lang/AssertionError
    //   16: dup
    //   17: invokespecial 369	java/lang/AssertionError:<init>	()V
    //   20: athrow
    //   21: aload_0
    //   22: aload_1
    //   23: invokevirtual 372	b/a/a/d:a	(Lb/a/a/a;)V
    //   26: aconst_null
    //   27: astore_1
    //   28: aload_0
    //   29: monitorenter
    //   30: aload_0
    //   31: getfield 101	b/a/a/d:n	Ljava/util/Map;
    //   34: invokeinterface 375 1 0
    //   39: ifne +246 -> 285
    //   42: aload_0
    //   43: getfield 101	b/a/a/d:n	Ljava/util/Map;
    //   46: invokeinterface 379 1 0
    //   51: aload_0
    //   52: getfield 101	b/a/a/d:n	Ljava/util/Map;
    //   55: invokeinterface 383 1 0
    //   60: anewarray 246	b/a/a/p
    //   63: invokeinterface 389 2 0
    //   68: checkcast 391	[Lb/a/a/p;
    //   71: astore 4
    //   73: aload_0
    //   74: getfield 101	b/a/a/d:n	Ljava/util/Map;
    //   77: invokeinterface 394 1 0
    //   82: aload_0
    //   83: iconst_0
    //   84: invokespecial 266	b/a/a/d:a	(Z)V
    //   87: aload_0
    //   88: getfield 396	b/a/a/d:u	Ljava/util/Map;
    //   91: ifnull +188 -> 279
    //   94: aload_0
    //   95: getfield 396	b/a/a/d:u	Ljava/util/Map;
    //   98: invokeinterface 379 1 0
    //   103: aload_0
    //   104: getfield 396	b/a/a/d:u	Ljava/util/Map;
    //   107: invokeinterface 383 1 0
    //   112: anewarray 398	b/a/a/z
    //   115: invokeinterface 389 2 0
    //   120: checkcast 400	[Lb/a/a/z;
    //   123: astore 5
    //   125: aload_0
    //   126: aconst_null
    //   127: putfield 396	b/a/a/d:u	Ljava/util/Map;
    //   130: aload_0
    //   131: monitorexit
    //   132: aload_1
    //   133: astore_3
    //   134: aload 4
    //   136: ifnull +67 -> 203
    //   139: aload 4
    //   141: arraylength
    //   142: istore 8
    //   144: iconst_0
    //   145: istore 7
    //   147: iload 7
    //   149: iload 8
    //   151: if_icmpge +50 -> 201
    //   154: aload 4
    //   156: iload 7
    //   158: aaload
    //   159: astore_3
    //   160: aload_3
    //   161: aload_2
    //   162: invokevirtual 401	b/a/a/p:a	(Lb/a/a/a;)V
    //   165: aload_1
    //   166: astore_3
    //   167: iload 7
    //   169: iconst_1
    //   170: iadd
    //   171: istore 7
    //   173: aload_3
    //   174: astore_1
    //   175: goto -28 -> 147
    //   178: astore_1
    //   179: goto -151 -> 28
    //   182: astore_1
    //   183: aload_0
    //   184: monitorexit
    //   185: aload_1
    //   186: athrow
    //   187: astore 6
    //   189: aload_1
    //   190: astore_3
    //   191: aload_1
    //   192: ifnull -25 -> 167
    //   195: aload 6
    //   197: astore_3
    //   198: goto -31 -> 167
    //   201: aload_1
    //   202: astore_3
    //   203: aload 5
    //   205: ifnull +35 -> 240
    //   208: aload 5
    //   210: arraylength
    //   211: istore 8
    //   213: iconst_0
    //   214: istore 7
    //   216: iload 7
    //   218: iload 8
    //   220: if_icmpge +20 -> 240
    //   223: aload 5
    //   225: iload 7
    //   227: aaload
    //   228: invokevirtual 403	b/a/a/z:c	()V
    //   231: iload 7
    //   233: iconst_1
    //   234: iadd
    //   235: istore 7
    //   237: goto -21 -> 216
    //   240: aload_0
    //   241: getfield 202	b/a/a/d:i	Lb/a/a/c;
    //   244: invokeinterface 406 1 0
    //   249: aload_3
    //   250: astore_1
    //   251: aload_0
    //   252: getfield 192	b/a/a/d:h	Ljava/net/Socket;
    //   255: invokevirtual 409	java/net/Socket:close	()V
    //   258: aload_1
    //   259: ifnull +15 -> 274
    //   262: aload_1
    //   263: athrow
    //   264: astore_1
    //   265: aload_3
    //   266: ifnull -15 -> 251
    //   269: aload_3
    //   270: astore_1
    //   271: goto -20 -> 251
    //   274: return
    //   275: astore_1
    //   276: goto -18 -> 258
    //   279: aconst_null
    //   280: astore 5
    //   282: goto -152 -> 130
    //   285: aconst_null
    //   286: astore 4
    //   288: goto -201 -> 87
    // Local variable table:
    //   start	length	slot	name	signature
    //   0	291	0	this	d
    //   0	291	1	parama1	a
    //   0	291	2	parama2	a
    //   133	137	3	localObject	Object
    //   71	216	4	arrayOfp	p[]
    //   123	158	5	arrayOfz	z[]
    //   187	9	6	localIOException	IOException
    //   145	91	7	i1	int
    //   142	79	8	i2	int
    // Exception table:
    //   from	to	target	type
    //   21	26	178	java/io/IOException
    //   30	87	182	finally
    //   87	130	182	finally
    //   130	132	182	finally
    //   183	185	182	finally
    //   160	165	187	java/io/IOException
    //   240	249	264	java/io/IOException
    //   251	258	275	java/io/IOException
  }
  
  private void a(boolean paramBoolean)
  {
    if (paramBoolean) {}
    for (;;)
    {
      try
      {
        l1 = System.nanoTime();
        this.s = l1;
        return;
      }
      finally {}
      long l1 = Long.MAX_VALUE;
    }
  }
  
  private void a(boolean paramBoolean, int paramInt1, int paramInt2, z paramz)
  {
    l.execute(new g(this, "OkHttp %s ping %08x%08x", new Object[] { this.o, Integer.valueOf(paramInt1), Integer.valueOf(paramInt2) }, paramBoolean, paramInt1, paramInt2, paramz));
  }
  
  private void b(boolean paramBoolean, int paramInt1, int paramInt2, z paramz)
  {
    c localc = this.i;
    if (paramz != null) {}
    try
    {
      paramz.a();
      this.i.a(paramBoolean, paramInt1, paramInt2);
      return;
    }
    finally {}
  }
  
  /* Error */
  private z c(int paramInt)
  {
    // Byte code:
    //   0: aload_0
    //   1: monitorenter
    //   2: aload_0
    //   3: getfield 396	b/a/a/d:u	Ljava/util/Map;
    //   6: ifnull +24 -> 30
    //   9: aload_0
    //   10: getfield 396	b/a/a/d:u	Ljava/util/Map;
    //   13: iload_1
    //   14: invokestatic 257	java/lang/Integer:valueOf	(I)Ljava/lang/Integer;
    //   17: invokeinterface 459 2 0
    //   22: checkcast 398	b/a/a/z
    //   25: astore_2
    //   26: aload_0
    //   27: monitorexit
    //   28: aload_2
    //   29: areturn
    //   30: aconst_null
    //   31: astore_2
    //   32: goto -6 -> 26
    //   35: astore_2
    //   36: aload_0
    //   37: monitorexit
    //   38: aload_2
    //   39: athrow
    // Local variable table:
    //   start	length	slot	name	signature
    //   0	40	0	this	d
    //   0	40	1	paramInt	int
    //   25	7	2	localz	z
    //   35	4	2	localObject	Object
    // Exception table:
    //   from	to	target	type
    //   2	26	35	finally
  }
  
  private void c(int paramInt, a parama)
  {
    this.t.execute(new k(this, "OkHttp %s Push Reset[%s]", new Object[] { this.o, Integer.valueOf(paramInt) }, paramInt, parama));
  }
  
  private boolean d(int paramInt)
  {
    return (this.a == ai.d) && (paramInt != 0) && ((paramInt & 0x1) == 0);
  }
  
  p a(int paramInt)
  {
    try
    {
      p localp = (p)this.n.get(Integer.valueOf(paramInt));
      return localp;
    }
    finally
    {
      localObject = finally;
      throw ((Throwable)localObject);
    }
  }
  
  public p a(List<r> paramList, boolean paramBoolean1, boolean paramBoolean2)
  {
    return a(0, paramList, paramBoolean1, paramBoolean2);
  }
  
  public ai a()
  {
    return this.a;
  }
  
  void a(int paramInt, long paramLong)
  {
    l.execute(new f(this, "OkHttp Window Update %s stream %d", new Object[] { this.o, Integer.valueOf(paramInt) }, paramInt, paramLong));
  }
  
  void a(int paramInt, a parama)
  {
    l.submit(new e(this, "OkHttp %s stream %d", new Object[] { this.o, Integer.valueOf(paramInt) }, paramInt, parama));
  }
  
  public void a(int paramInt, boolean paramBoolean, c.e parame, long paramLong)
  {
    long l1 = paramLong;
    if (paramLong == 0L)
    {
      this.i.a(paramBoolean, paramInt, parame, 0);
      return;
    }
    for (;;)
    {
      try
      {
        int i1 = Math.min((int)Math.min(l1, this.d), this.i.c());
        this.d -= i1;
        l1 -= i1;
        c localc = this.i;
        if ((!paramBoolean) || (l1 != 0L)) {
          break label170;
        }
        bool = true;
        localc.a(bool, paramInt, parame, i1);
        if (l1 <= 0L) {
          break;
        }
        try
        {
          if (this.d > 0L) {
            continue;
          }
          if (!this.n.containsKey(Integer.valueOf(paramInt))) {
            throw new IOException("stream closed");
          }
        }
        catch (InterruptedException parame)
        {
          throw new InterruptedIOException();
        }
        wait();
      }
      finally {}
      continue;
      label170:
      boolean bool = false;
    }
  }
  
  void a(long paramLong)
  {
    this.d += paramLong;
    if (paramLong > 0L) {
      notifyAll();
    }
  }
  
  public void a(a parama)
  {
    int i1;
    synchronized (this.i) {}
  }
  
  public int b()
  {
    try
    {
      int i1 = this.f.d(Integer.MAX_VALUE);
      return i1;
    }
    finally
    {
      localObject = finally;
      throw ((Throwable)localObject);
    }
  }
  
  p b(int paramInt)
  {
    try
    {
      p localp = (p)this.n.remove(Integer.valueOf(paramInt));
      if ((localp != null) && (this.n.isEmpty())) {
        a(true);
      }
      notifyAll();
      return localp;
    }
    finally {}
  }
  
  void b(int paramInt, a parama)
  {
    this.i.a(paramInt, parama);
  }
  
  public void c()
  {
    this.i.b();
  }
  
  public void close()
  {
    a(a.a, a.l);
  }
  
  public void d()
  {
    this.i.a();
    this.i.b(this.e);
    int i1 = this.e.f(65536);
    if (i1 != 65536) {
      this.i.a(0, i1 - 65536);
    }
  }
  
  public static class a
  {
    private Socket a;
    private String b;
    private c.h c;
    private c.g d;
    private d.b e = d.b.a;
    private ai f = ai.c;
    private aa g = aa.a;
    private boolean h;
    
    public a(boolean paramBoolean)
    {
      this.h = paramBoolean;
    }
    
    public a a(d.b paramb)
    {
      this.e = paramb;
      return this;
    }
    
    public a a(ai paramai)
    {
      this.f = paramai;
      return this;
    }
    
    public a a(Socket paramSocket, String paramString, c.h paramh, c.g paramg)
    {
      this.a = paramSocket;
      this.b = paramString;
      this.c = paramh;
      this.d = paramg;
      return this;
    }
    
    public d a()
    {
      return new d(this, null);
    }
  }
  
  public static abstract class b
  {
    public static final b a = new l();
    
    public void a(d paramd) {}
    
    public abstract void a(p paramp);
  }
  
  class c
    extends b.a.f
    implements b.a
  {
    final b a;
    
    private c(b paramb)
    {
      super(new Object[] { d.a(d.this) });
      this.a = paramb;
    }
    
    private void a(ac paramac)
    {
      d.e().execute(new o(this, "OkHttp %s ACK Settings", new Object[] { d.a(d.this) }, paramac));
    }
    
    public void a() {}
    
    public void a(int paramInt1, int paramInt2, int paramInt3, boolean paramBoolean) {}
    
    public void a(int paramInt1, int paramInt2, List<r> paramList)
    {
      d.a(d.this, paramInt2, paramList);
    }
    
    public void a(int paramInt, long paramLong)
    {
      if (paramInt == 0) {
        synchronized (d.this)
        {
          d locald = d.this;
          locald.d += paramLong;
          d.this.notifyAll();
          return;
        }
      }
      ??? = d.this.a(paramInt);
      if (??? != null) {
        try
        {
          ((p)???).a(paramLong);
          return;
        }
        finally {}
      }
    }
    
    public void a(int paramInt, a parama)
    {
      if (d.a(d.this, paramInt)) {
        d.a(d.this, paramInt, parama);
      }
      p localp;
      do
      {
        return;
        localp = d.this.b(paramInt);
      } while (localp == null);
      localp.c(parama);
    }
    
    public void a(int paramInt, a arg2, c.i parami)
    {
      if (parami.f() > 0) {}
      synchronized (d.this)
      {
        parami = (p[])d.e(d.this).values().toArray(new p[d.e(d.this).size()]);
        d.b(d.this, true);
        int j = parami.length;
        int i = 0;
        if (i < j)
        {
          ??? = parami[i];
          if ((???.a() > paramInt) && (???.c()))
          {
            ???.c(a.k);
            d.this.b(???.a());
          }
          i += 1;
        }
      }
    }
    
    public void a(boolean paramBoolean, int paramInt1, int paramInt2)
    {
      if (paramBoolean)
      {
        z localz = d.c(d.this, paramInt1);
        if (localz != null) {
          localz.b();
        }
        return;
      }
      d.b(d.this, true, paramInt1, paramInt2, null);
    }
    
    public void a(boolean paramBoolean, int paramInt1, c.h paramh, int paramInt2)
    {
      if (d.a(d.this, paramInt1)) {
        d.a(d.this, paramInt1, paramh, paramInt2, paramBoolean);
      }
      p localp;
      do
      {
        return;
        localp = d.this.a(paramInt1);
        if (localp == null)
        {
          d.this.a(paramInt1, a.c);
          paramh.g(paramInt2);
          return;
        }
        localp.a(paramh, paramInt2);
      } while (!paramBoolean);
      localp.i();
    }
    
    public void a(boolean paramBoolean, ac paramac)
    {
      for (;;)
      {
        int i;
        synchronized (d.this)
        {
          i = d.this.f.f(65536);
          if (paramBoolean) {
            d.this.f.a();
          }
          d.this.f.a(paramac);
          if (d.this.a() == ai.d) {
            a(paramac);
          }
          int j = d.this.f.f(65536);
          if ((j == -1) || (j == i)) {
            break label277;
          }
          l = j - i;
          if (!d.g(d.this))
          {
            d.this.a(l);
            d.a(d.this, true);
          }
          if (d.e(d.this).isEmpty()) {
            break label272;
          }
          paramac = (p[])d.e(d.this).values().toArray(new p[d.e(d.this).size()]);
          d.e().execute(new n(this, "OkHttp %s settings", new Object[] { d.a(d.this) }));
          if ((paramac == null) || (l == 0L)) {
            break label271;
          }
          j = paramac.length;
          i = 0;
          if (i >= j) {
            break label271;
          }
        }
        synchronized (paramac[i])
        {
          ???.a(l);
          i += 1;
          continue;
          paramac = finally;
          throw paramac;
        }
        label271:
        return;
        label272:
        paramac = null;
        continue;
        label277:
        paramac = null;
        long l = 0L;
      }
    }
    
    public void a(boolean paramBoolean1, boolean paramBoolean2, int paramInt1, int paramInt2, List<r> paramList, s params)
    {
      if (d.a(d.this, paramInt1)) {
        d.a(d.this, paramInt1, paramList, paramBoolean2);
      }
      p localp;
      do
      {
        return;
        synchronized (d.this)
        {
          if (d.b(d.this)) {
            return;
          }
        }
        localp = d.this.a(paramInt1);
        if (localp == null)
        {
          if (params.a())
          {
            d.this.a(paramInt1, a.c);
            return;
          }
          if (paramInt1 <= d.c(d.this)) {
            return;
          }
          if (paramInt1 % 2 == d.d(d.this) % 2) {
            return;
          }
          paramList = new p(paramInt1, d.this, paramBoolean1, paramBoolean2, paramList);
          d.b(d.this, paramInt1);
          d.e(d.this).put(Integer.valueOf(paramInt1), paramList);
          d.e().execute(new m(this, "OkHttp %s stream %d", new Object[] { d.a(d.this), Integer.valueOf(paramInt1) }, paramList));
          return;
        }
        if (params.b())
        {
          localp.b(a.b);
          d.this.b(paramInt1);
          return;
        }
        localp.a(paramList, params);
      } while (!paramBoolean2);
      localp.i();
    }
    
    /* Error */
    protected void b()
    {
      // Byte code:
      //   0: getstatic 249	b/a/a/a:g	Lb/a/a/a;
      //   3: astore_3
      //   4: getstatic 249	b/a/a/a:g	Lb/a/a/a;
      //   7: astore 4
      //   9: aload_3
      //   10: astore_2
      //   11: aload_3
      //   12: astore_1
      //   13: aload_0
      //   14: getfield 16	b/a/a/d$c:c	Lb/a/a/d;
      //   17: getfield 252	b/a/a/d:b	Z
      //   20: ifne +16 -> 36
      //   23: aload_3
      //   24: astore_2
      //   25: aload_3
      //   26: astore_1
      //   27: aload_0
      //   28: getfield 28	b/a/a/d$c:a	Lb/a/a/b;
      //   31: invokeinterface 255 1 0
      //   36: aload_3
      //   37: astore_2
      //   38: aload_3
      //   39: astore_1
      //   40: aload_0
      //   41: getfield 28	b/a/a/d$c:a	Lb/a/a/b;
      //   44: aload_0
      //   45: invokeinterface 258 2 0
      //   50: ifne -14 -> 36
      //   53: aload_3
      //   54: astore_2
      //   55: aload_3
      //   56: astore_1
      //   57: getstatic 260	b/a/a/a:a	Lb/a/a/a;
      //   60: astore_3
      //   61: aload_3
      //   62: astore_2
      //   63: aload_3
      //   64: astore_1
      //   65: getstatic 263	b/a/a/a:l	Lb/a/a/a;
      //   68: astore 5
      //   70: aload_0
      //   71: getfield 16	b/a/a/d$c:c	Lb/a/a/d;
      //   74: aload_3
      //   75: aload 5
      //   77: invokestatic 266	b/a/a/d:a	(Lb/a/a/d;Lb/a/a/a;Lb/a/a/a;)V
      //   80: aload_0
      //   81: getfield 28	b/a/a/d$c:a	Lb/a/a/b;
      //   84: invokestatic 271	b/a/j:a	(Ljava/io/Closeable;)V
      //   87: return
      //   88: astore_1
      //   89: aload_2
      //   90: astore_1
      //   91: getstatic 239	b/a/a/a:b	Lb/a/a/a;
      //   94: astore_3
      //   95: getstatic 239	b/a/a/a:b	Lb/a/a/a;
      //   98: astore_1
      //   99: aload_0
      //   100: getfield 16	b/a/a/d$c:c	Lb/a/a/d;
      //   103: aload_3
      //   104: aload_1
      //   105: invokestatic 266	b/a/a/d:a	(Lb/a/a/d;Lb/a/a/a;Lb/a/a/a;)V
      //   108: aload_0
      //   109: getfield 28	b/a/a/d$c:a	Lb/a/a/b;
      //   112: invokestatic 271	b/a/j:a	(Ljava/io/Closeable;)V
      //   115: return
      //   116: astore_2
      //   117: aload_1
      //   118: astore_3
      //   119: aload_2
      //   120: astore_1
      //   121: aload_0
      //   122: getfield 16	b/a/a/d$c:c	Lb/a/a/d;
      //   125: aload_3
      //   126: aload 4
      //   128: invokestatic 266	b/a/a/d:a	(Lb/a/a/d;Lb/a/a/a;Lb/a/a/a;)V
      //   131: aload_0
      //   132: getfield 28	b/a/a/d$c:a	Lb/a/a/b;
      //   135: invokestatic 271	b/a/j:a	(Ljava/io/Closeable;)V
      //   138: aload_1
      //   139: athrow
      //   140: astore_2
      //   141: goto -10 -> 131
      //   144: astore_1
      //   145: goto -24 -> 121
      //   148: astore_1
      //   149: goto -41 -> 108
      //   152: astore_1
      //   153: goto -73 -> 80
      // Local variable table:
      //   start	length	slot	name	signature
      //   0	156	0	this	c
      //   12	53	1	localObject1	Object
      //   88	1	1	localIOException1	IOException
      //   90	49	1	localObject2	Object
      //   144	1	1	localObject3	Object
      //   148	1	1	localIOException2	IOException
      //   152	1	1	localIOException3	IOException
      //   10	80	2	localObject4	Object
      //   116	4	2	localObject5	Object
      //   140	1	2	localIOException4	IOException
      //   3	123	3	localObject6	Object
      //   7	120	4	locala1	a
      //   68	8	5	locala2	a
      // Exception table:
      //   from	to	target	type
      //   13	23	88	java/io/IOException
      //   27	36	88	java/io/IOException
      //   40	53	88	java/io/IOException
      //   57	61	88	java/io/IOException
      //   65	70	88	java/io/IOException
      //   13	23	116	finally
      //   27	36	116	finally
      //   40	53	116	finally
      //   57	61	116	finally
      //   65	70	116	finally
      //   91	95	116	finally
      //   121	131	140	java/io/IOException
      //   95	99	144	finally
      //   99	108	148	java/io/IOException
      //   70	80	152	java/io/IOException
    }
  }
}


/* Location:              E:\apk\xiaoenai2\classes-dex2jar.jar!\b\a\a\d.class
 * Java compiler version: 6 (50.0)
 * JD-Core Version:       0.7.1
 */